{"Chapter Number": 7, "Chapter Name": "Edible vegetables and certain roots and tubers ", "Pre-Table Notes": "Chapter 7\nEdible vegetables and certain roots and tubers\nNotes.\n1.- This Chapter does not cover forage products of heading 12.14.\n2.- In headings 07.09, 07.10, 07.11 and 07.12 the word \u201cvegetables\u201d includes edible mushrooms, truffles, olives, capers, marrows, pumpkins, aubergines, sweet corn\n(Zea mays var. saccharata), fruits of the genus Capsicum or of the genus Pimenta, fennel, parsley, chervil, tarragon, cress and sweet marjoram (Majorana\nhortensis or Origanum majorana).\n3.- Heading 07.12 covers all dried vegetables of the kinds falling in headings 07.01 to 07.11, other than :\n(a) dried leguminous vegetables, shelled (heading 07.13);\n(b) sweet corn in the forms specified in headings 11.02 to 11.04;\n(c) flour, meal, powder, flakes, granules and pellets of potatoes (heading 11.05);\n(d) flour, meal and powder of the dried leguminous vegetables of heading 07.13 (heading 11.06).\n4.- However, dried or crushed or ground fruits of the genus Capsicum or of the genus Pimenta are excluded from this Chapter (heading 09.04).\n5.- Heading 07.11 applies to vegetables which have been treated solely to ensure their provisional preservation during transport or storage prior to use (for example,\nby sulphur dioxide gas, in brine, in sulphur water or in other preservative solutions), provided they remain unsuitable for immediate consumption in that state.", "Items": [{"Prefix": "", "HS Hdg Name": "Potatoes, fresh or chilled (+).", "HS Hdg": "07.01", "HS Code": "0701.10.00N", "Description": "Seed", "Unit": "kg", "ICL/SLSI": "", "Preferential Duty_AP": "", "Preferential Duty_AD": "", "Preferential Duty_BN": "", "Preferential Duty_GT": "", "Preferential Duty_IN": "", "Preferential Duty_PK": "Free", "Preferential Duty_SA": "", "Preferential Duty_SF": "Free", "Preferential Duty_SD": "", "Preferential Duty_SG": "Free", "Gen Duty": "Free", "VAT": "Ex", "PAL_Gen": "10%", "PAL_SG": "6%", "Cess_GEN": "", "Cess_SG": "", "Excise SPD": "", "SSCL": "2.5%", "SCL": "", "SC Code": ""}, {"Prefix": "", "HS Hdg Name": "Potatoes, fresh or chilled (+).", "HS Hdg": "07.01", "HS Code": "0701.90.00N", "Description": "Other", "Unit": "kg", "ICL/SLSI": "", "Preferential Duty_AP": "", "Preferential Duty_AD": "", "Preferential Duty_BN": "", "Preferential Duty_GT": "", "Preferential Duty_IN": "", "Preferential Duty_PK": "", "Preferential Duty_SA": "", "Preferential Duty_SF": "", "Preferential Duty_SD": "", "Preferential Duty_SG": "", "Gen Duty": "Rs.20/=\nper kg", "VAT": "18%", "PAL_Gen": "Ex", "PAL_SG": "", "Cess_GEN": "", "Cess_SG": "", "Excise SPD": "", "SSCL": "2.5%", "SCL": "*", "SC Code": ""}, {"Prefix": "", "HS Hdg Name": "Potatoes, fresh or chilled (+).", "HS Hdg": "07.01", "HS Code": "0702.00.00N", "Description": "Tomatoes, fresh or chilled.", "Unit": "kg", "ICL/SLSI": "", "Preferential Duty_AP": "", "Preferential Duty_AD": "", "Preferential Duty_BN": "", "Preferential Duty_GT": "", "Preferential Duty_IN": "", "Preferential Duty_PK": "", "Preferential Duty_SA": "", "Preferential Duty_SF": "", "Preferential Duty_SD": "", "Preferential Duty_SG": "", "Gen Duty": "20%", "VAT": "18%", "PAL_Gen": "Ex", "PAL_SG": "", "Cess_GEN": "40% or\nRs.270/=\nper kg", "Cess_SG": "", "Excise SPD": "", "SSCL": "2.5%", "SCL": "", "SC Code": ""}, {"Prefix": "Onions and shallots :", "HS Hdg Name": "Onions, shallots, garlic, leeks and other\nalliaceous vegetables, fresh or chilled.", "HS Hdg": "07.03", "HS Code": "0703.10.10N", "Description": "Red onions", "Unit": "kg", "ICL/SLSI": "", "Preferential Duty_AP": "", "Preferential Duty_AD": "", "Preferential Duty_BN": "", "Preferential Duty_GT": "", "Preferential Duty_IN": "", "Preferential Duty_PK": "", "Preferential Duty_SA": "", "Preferential Duty_SF": "", "Preferential Duty_SD": "", "Preferential Duty_SG": "", "Gen Duty": "Rs.30/=\nper kg", "VAT": "18%", "PAL_Gen": "Ex", "PAL_SG": "", "Cess_GEN": "", "Cess_SG": "", "Excise SPD": "", "SSCL": "2.5%", "SCL": "*", "SC Code": ""}, {"Prefix": "Onions and shallots :", "HS Hdg Name": "Onions, shallots, garlic, leeks and other\nalliaceous vegetables, fresh or chilled.", "HS Hdg": "07.03", "HS Code": "0703.10.20N", "Description": "B' onions", "Unit": "kg", "ICL/SLSI": "", "Preferential Duty_AP": "", "Preferential Duty_AD": "", "Preferential Duty_BN": "", "Preferential Duty_GT": "", "Preferential Duty_IN": "", "Preferential Duty_PK": "", "Preferential Duty_SA": "", "Preferential Duty_SF": "", "Preferential Duty_SD": "", "Preferential Duty_SG": "", "Gen Duty": "20% or\nRs.30/=\nper kg", "VAT": "18%", "PAL_Gen": "Ex", "PAL_SG": "", "Cess_GEN": "10% or\nRs.20/= per\nkg", "Cess_SG": "", "Excise SPD": "", "SSCL": "2.5%", "SCL": "*", "SC Code": ""}, {"Prefix": "Onions and shallots :", "HS Hdg Name": "Onions, shallots, garlic, leeks and other\nalliaceous vegetables, fresh or chilled.", "HS Hdg": "07.03", "HS Code": "0703.10.30N", "Description": "Other onions", "Unit": "kg", "ICL/SLSI": "", "Preferential Duty_AP": "", "Preferential Duty_AD": "", "Preferential Duty_BN": "", "Preferential Duty_GT": "", "Preferential Duty_IN": "", "Preferential Duty_PK": "", "Preferential Duty_SA": "", "Preferential Duty_SF": "", "Preferential Duty_SD": "", "Preferential Duty_SG": "", "Gen Duty": "Rs.15/=\nper kg", "VAT": "18%", "PAL_Gen": "Ex", "PAL_SG": "", "Cess_GEN": "", "Cess_SG": "", "Excise SPD": "", "SSCL": "2.5%", "SCL": "", "SC Code": ""}, {"Prefix": "", "HS Hdg Name": "Onions, shallots, garlic, leeks and other\nalliaceous vegetables, fresh or chilled.", "HS Hdg": "07.03", "HS Code": "0703.10.90N", "Description": "Other", "Unit": "kg", "ICL/SLSI": "", "Preferential Duty_AP": "", "Preferential Duty_AD": "", "Preferential Duty_BN": "", "Preferential Duty_GT": "", "Preferential Duty_IN": "", "Preferential Duty_PK": "", "Preferential Duty_SA": "", "Preferential Duty_SF": "", "Preferential Duty_SD": "", "Preferential Duty_SG": "", "Gen Duty": "Rs.30/=\nper kg", "VAT": "18%", "PAL_Gen": "10%", "PAL_SG": "", "Cess_GEN": "", "Cess_SG": "", "Excise SPD": "", "SSCL": "2.5%", "SCL": "", "SC Code": ""}, {"Prefix": "", "HS Hdg Name": "Onions, shallots, garlic, leeks and other\nalliaceous vegetables, fresh or chilled.", "HS Hdg": "07.03", "HS Code": "0703.20.00N", "Description": "Garlic", "Unit": "kg", "ICL/SLSI": "", "Preferential Duty_AP": "", "Preferential Duty_AD": "", "Preferential Duty_BN": "", "Preferential Duty_GT": "", "Preferential Duty_IN": "Free", "Preferential Duty_PK": "Free", "Preferential Duty_SA": "", "Preferential Duty_SF": "5%", "Preferential Duty_SD": "4.5%", "Preferential Duty_SG": "", "Gen Duty": "15%", "VAT": "18%", "PAL_Gen": "Ex", "PAL_SG": "", "Cess_GEN": "0%", "Cess_SG": "", "Excise SPD": "", "SSCL": "2.5%", "SCL": "*", "SC Code": ""}, {"Prefix": "", "HS Hdg Name": "Onions, shallots, garlic, leeks and other\nalliaceous vegetables, fresh or chilled.", "HS Hdg": "07.03", "HS Code": "0703.90.00N", "Description": "Leeks and other alliaceous vegetables", "Unit": "kg", "ICL/SLSI": "", "Preferential Duty_AP": "", "Preferential Duty_AD": "", "Preferential Duty_BN": "", "Preferential Duty_GT": "", "Preferential Duty_IN": "", "Preferential Duty_PK": "", "Preferential Duty_SA": "", "Preferential Duty_SF": "", "Preferential Duty_SD": "", "Preferential Duty_SG": "", "Gen Duty": "20%", "VAT": "18%", "PAL_Gen": "Ex", "PAL_SG": "", "Cess_GEN": "40% or\nRs.140/=\nper kg", "Cess_SG": "", "Excise SPD": "", "SSCL": "2.5%", "SCL": "", "SC Code": ""}, {"Prefix": "", "HS Hdg Name": "Cabbages, cauliflowers, kohlrabi, kale and\nsimilar edible brassicas, fresh or chilled.", "HS Hdg": "07.04", "HS Code": "0704.10.00N", "Description": "Cauliflowers and broccoli", "Unit": "kg", "ICL/SLSI": "", "Preferential Duty_AP": "", "Preferential Duty_AD": "", "Preferential Duty_BN": "", "Preferential Duty_GT": "", "Preferential Duty_IN": "", "Preferential Duty_PK": "", "Preferential Duty_SA": "", "Preferential Duty_SF": "", "Preferential Duty_SD": "", "Preferential Duty_SG": "", "Gen Duty": "20%", "VAT": "18%", "PAL_Gen": "Ex", "PAL_SG": "", "Cess_GEN": "40% or\nRs.180/=\nper kg", "Cess_SG": "", "Excise SPD": "", "SSCL": "2.5%", "SCL": "", "SC Code": ""}, {"Prefix": "", "HS Hdg Name": "Cabbages, cauliflowers, kohlrabi, kale and\nsimilar edible brassicas, fresh or chilled.", "HS Hdg": "07.04", "HS Code": "0704.20.00N", "Description": "Brussels sprouts", "Unit": "kg", "ICL/SLSI": "", "Preferential Duty_AP": "", "Preferential Duty_AD": "", "Preferential Duty_BN": "", "Preferential Duty_GT": "", "Preferential Duty_IN": "", "Preferential Duty_PK": "", "Preferential Duty_SA": "", "Preferential Duty_SF": "", "Preferential Duty_SD": "", "Preferential Duty_SG": "", "Gen Duty": "20%", "VAT": "18%", "PAL_Gen": "Ex", "PAL_SG": "", "Cess_GEN": "40% or\nRs.180/=\nper kg", "Cess_SG": "", "Excise SPD": "", "SSCL": "2.5%", "SCL": "", "SC Code": ""}, {"Prefix": "", "HS Hdg Name": "Cabbages, cauliflowers, kohlrabi, kale and\nsimilar edible brassicas, fresh or chilled.", "HS Hdg": "07.04", "HS Code": "0704.90.00N", "Description": "Other", "Unit": "kg", "ICL/SLSI": "", "Preferential Duty_AP": "", "Preferential Duty_AD": "", "Preferential Duty_BN": "", "Preferential Duty_GT": "", "Preferential Duty_IN": "", "Preferential Duty_PK": "", "Preferential Duty_SA": "", "Preferential Duty_SF": "", "Preferential Duty_SD": "", "Preferential Duty_SG": "", "Gen Duty": "20%", "VAT": "18%", "PAL_Gen": "Ex", "PAL_SG": "", "Cess_GEN": "40% or\nRs.180/=\nper kg", "Cess_SG": "", "Excise SPD": "", "SSCL": "2.5%", "SCL": "", "SC Code": ""}, {"Prefix": "Lettuce :", "HS Hdg Name": "Lettuce (Lactuca sativa) and chicory\n(Cichorium spp.), fresh or chilled.", "HS Hdg": "07.05", "HS Code": "0705.11.00N", "Description": "Cabbage lettuce (head lettuce)", "Unit": "kg", "ICL/SLSI": "", "Preferential Duty_AP": "", "Preferential Duty_AD": "", "Preferential Duty_BN": "", "Preferential Duty_GT": "", "Preferential Duty_IN": "", "Preferential Duty_PK": "", "Preferential Duty_SA": "", "Preferential Duty_SF": "", "Preferential Duty_SD": "", "Preferential Duty_SG": "", "Gen Duty": "20%", "VAT": "18%", "PAL_Gen": "Ex", "PAL_SG": "", "Cess_GEN": "40% or\nRs.180/=\nper kg", "Cess_SG": "", "Excise SPD": "", "SSCL": "2.5%", "SCL": "", "SC Code": ""}, {"Prefix": "Lettuce :", "HS Hdg Name": "Lettuce (Lactuca sativa) and chicory\n(Cichorium spp.), fresh or chilled.", "HS Hdg": "07.05", "HS Code": "0705.19.00N", "Description": "Other", "Unit": "kg", "ICL/SLSI": "", "Preferential Duty_AP": "", "Preferential Duty_AD": "", "Preferential Duty_BN": "", "Preferential Duty_GT": "", "Preferential Duty_IN": "", "Preferential Duty_PK": "", "Preferential Duty_SA": "", "Preferential Duty_SF": "", "Preferential Duty_SD": "", "Preferential Duty_SG": "", "Gen Duty": "20%", "VAT": "18%", "PAL_Gen": "Ex", "PAL_SG": "", "Cess_GEN": "40% or\nRs.180/=\nper kg", "Cess_SG": "", "Excise SPD": "", "SSCL": "2.5%", "SCL": "", "SC Code": ""}, {"Prefix": "Chicory :", "HS Hdg Name": "Lettuce (Lactuca sativa) and chicory\n(Cichorium spp.), fresh or chilled.", "HS Hdg": "07.05", "HS Code": "0705.21.00N", "Description": "Witloof chicory (Cichorium intybus var. foliosum)", "Unit": "kg", "ICL/SLSI": "", "Preferential Duty_AP": "", "Preferential Duty_AD": "", "Preferential Duty_BN": "", "Preferential Duty_GT": "", "Preferential Duty_IN": "", "Preferential Duty_PK": "Free", "Preferential Duty_SA": "", "Preferential Duty_SF": "", "Preferential Duty_SD": "", "Preferential Duty_SG": "", "Gen Duty": "20%", "VAT": "18%", "PAL_Gen": "Ex", "PAL_SG": "", "Cess_GEN": "40% or\nRs.180/=\nper kg", "Cess_SG": "", "Excise SPD": "", "SSCL": "2.5%", "SCL": "", "SC Code": ""}, {"Prefix": "Chicory :", "HS Hdg Name": "Lettuce (Lactuca sativa) and chicory\n(Cichorium spp.), fresh or chilled.", "HS Hdg": "07.05", "HS Code": "0705.29.00N", "Description": "Other", "Unit": "kg", "ICL/SLSI": "", "Preferential Duty_AP": "", "Preferential Duty_AD": "", "Preferential Duty_BN": "", "Preferential Duty_GT": "", "Preferential Duty_IN": "", "Preferential Duty_PK": "Free", "Preferential Duty_SA": "", "Preferential Duty_SF": "", "Preferential Duty_SD": "", "Preferential Duty_SG": "", "Gen Duty": "20%", "VAT": "18%", "PAL_Gen": "Ex", "PAL_SG": "", "Cess_GEN": "40% or\nRs.180/=\nper kg", "Cess_SG": "", "Excise SPD": "", "SSCL": "2.5%", "SCL": "", "SC Code": ""}, {"Prefix": "", "HS Hdg Name": "Carrots, turnips, salad beetroot, salsify,\nceleriac, radishes and similar edible roots,\nfresh or chilled.", "HS Hdg": "07.06", "HS Code": "0706.10.00N", "Description": "Carrots and turnips", "Unit": "kg", "ICL/SLSI": "", "Preferential Duty_AP": "", "Preferential Duty_AD": "", "Preferential Duty_BN": "", "Preferential Duty_GT": "", "Preferential Duty_IN": "", "Preferential Duty_PK": "", "Preferential Duty_SA": "", "Preferential Duty_SF": "", "Preferential Duty_SD": "", "Preferential Duty_SG": "", "Gen Duty": "20%", "VAT": "18%", "PAL_Gen": "Ex", "PAL_SG": "", "Cess_GEN": "40% or\nRs.180/=\nper kg", "Cess_SG": "", "Excise SPD": "", "SSCL": "2.5%", "SCL": "", "SC Code": ""}, {"Prefix": "", "HS Hdg Name": "Carrots, turnips, salad beetroot, salsify,\nceleriac, radishes and similar edible roots,\nfresh or chilled.", "HS Hdg": "07.06", "HS Code": "0706.90.00N", "Description": "Other", "Unit": "kg", "ICL/SLSI": "", "Preferential Duty_AP": "", "Preferential Duty_AD": "", "Preferential Duty_BN": "", "Preferential Duty_GT": "", "Preferential Duty_IN": "", "Preferential Duty_PK": "", "Preferential Duty_SA": "", "Preferential Duty_SF": "", "Preferential Duty_SD": "", "Preferential Duty_SG": "", "Gen Duty": "20%", "VAT": "18%", "PAL_Gen": "Ex", "PAL_SG": "", "Cess_GEN": "40% or\nRs.180/=\nper kg", "Cess_SG": "", "Excise SPD": "", "SSCL": "2.5%", "SCL": "", "SC Code": ""}, {"Prefix": "", "HS Hdg Name": "Cucumbers and gherkins, fresh or chilled", "HS Hdg": "07.07", "HS Code": "0707.00.10N", "Description": "Cucumbers", "Unit": "kg", "ICL/SLSI": "", "Preferential Duty_AP": "", "Preferential Duty_AD": "", "Preferential Duty_BN": "", "Preferential Duty_GT": "", "Preferential Duty_IN": "", "Preferential Duty_PK": "", "Preferential Duty_SA": "", "Preferential Duty_SF": "", "Preferential Duty_SD": "", "Preferential Duty_SG": "", "Gen Duty": "20%", "VAT": "18%", "PAL_Gen": "Ex", "PAL_SG": "", "Cess_GEN": "40% or\nRs.180/=\nper kg", "Cess_SG": "", "Excise SPD": "", "SSCL": "2.5%", "SCL": "", "SC Code": ""}, {"Prefix": "", "HS Hdg Name": "Cucumbers and gherkins, fresh or chilled", "HS Hdg": "07.07", "HS Code": "0707.00.20N", "Description": "Gherkins", "Unit": "kg", "ICL/SLSI": "", "Preferential Duty_AP": "", "Preferential Duty_AD": "", "Preferential Duty_BN": "", "Preferential Duty_GT": "", "Preferential Duty_IN": "", "Preferential Duty_PK": "", "Preferential Duty_SA": "", "Preferential Duty_SF": "", "Preferential Duty_SD": "", "Preferential Duty_SG": "", "Gen Duty": "20%", "VAT": "18%", "PAL_Gen": "Ex", "PAL_SG": "", "Cess_GEN": "40% or\nRs.180/=\nper kg", "Cess_SG": "", "Excise SPD": "", "SSCL": "2.5%", "SCL": "", "SC Code": ""}, {"Prefix": "", "HS Hdg Name": "Leguminous vegetables, shelled or unshelled,\nfresh or chilled.", "HS Hdg": "07.08", "HS Code": "0708.10.00N", "Description": "Peas (Pisum sativum)", "Unit": "kg", "ICL/SLSI": "", "Preferential Duty_AP": "", "Preferential Duty_AD": "", "Preferential Duty_BN": "", "Preferential Duty_GT": "", "Preferential Duty_IN": "", "Preferential Duty_PK": "Free", "Preferential Duty_SA": "", "Preferential Duty_SF": "", "Preferential Duty_SD": "", "Preferential Duty_SG": "", "Gen Duty": "20%", "VAT": "18%", "PAL_Gen": "Ex", "PAL_SG": "", "Cess_GEN": "40% or\nRs.180/=\nper kg", "Cess_SG": "", "Excise SPD": "", "SSCL": "2.5%", "SCL": "", "SC Code": ""}, {"Prefix": "", "HS Hdg Name": "Leguminous vegetables, shelled or unshelled,\nfresh or chilled.", "HS Hdg": "07.08", "HS Code": "0708.20.00N", "Description": "Beans (Vigna spp., Phaseolus spp.)", "Unit": "kg", "ICL/SLSI": "", "Preferential Duty_AP": "", "Preferential Duty_AD": "", "Preferential Duty_BN": "", "Preferential Duty_GT": "", "Preferential Duty_IN": "", "Preferential Duty_PK": "", "Preferential Duty_SA": "", "Preferential Duty_SF": "", "Preferential Duty_SD": "", "Preferential Duty_SG": "", "Gen Duty": "20%", "VAT": "18%", "PAL_Gen": "Ex", "PAL_SG": "", "Cess_GEN": "40% or\nRs.180/=\nper kg", "Cess_SG": "", "Excise SPD": "", "SSCL": "2.5%", "SCL": "", "SC Code": ""}, {"Prefix": "", "HS Hdg Name": "Leguminous vegetables, shelled or unshelled,\nfresh or chilled.", "HS Hdg": "07.08", "HS Code": "0708.90.00N", "Description": "Other leguminous vegetables", "Unit": "kg", "ICL/SLSI": "", "Preferential Duty_AP": "", "Preferential Duty_AD": "", "Preferential Duty_BN": "", "Preferential Duty_GT": "", "Preferential Duty_IN": "", "Preferential Duty_PK": "", "Preferential Duty_SA": "", "Preferential Duty_SF": "", "Preferential Duty_SD": "", "Preferential Duty_SG": "", "Gen Duty": "20%", "VAT": "18%", "PAL_Gen": "Ex", "PAL_SG": "", "Cess_GEN": "40% or\nRs.180/=\nper kg", "Cess_SG": "", "Excise SPD": "", "SSCL": "2.5%", "SCL": "", "SC Code": ""}, {"Prefix": "", "HS Hdg Name": "Other vegetables, fresh or chilled.", "HS Hdg": "07.09", "HS Code": "0709.20.00N", "Description": "Asparagus", "Unit": "kg", "ICL/SLSI": "", "Preferential Duty_AP": "", "Preferential Duty_AD": "", "Preferential Duty_BN": "", "Preferential Duty_GT": "", "Preferential Duty_IN": "", "Preferential Duty_PK": "", "Preferential Duty_SA": "", "Preferential Duty_SF": "", "Preferential Duty_SD": "", "Preferential Duty_SG": "", "Gen Duty": "20%", "VAT": "18%", "PAL_Gen": "Ex", "PAL_SG": "", "Cess_GEN": "40% or\nRs.180/=\nper kg", "Cess_SG": "", "Excise SPD": "", "SSCL": "2.5%", "SCL": "", "SC Code": ""}, {"Prefix": "", "HS Hdg Name": "Other vegetables, fresh or chilled.", "HS Hdg": "07.09", "HS Code": "0709.30.00N", "Description": "Aubergines (egg-plants)", "Unit": "kg", "ICL/SLSI": "", "Preferential Duty_AP": "", "Preferential Duty_AD": "", "Preferential Duty_BN": "", "Preferential Duty_GT": "", "Preferential Duty_IN": "", "Preferential Duty_PK": "", "Preferential Duty_SA": "", "Preferential Duty_SF": "", "Preferential Duty_SD": "", "Preferential Duty_SG": "", "Gen Duty": "20%", "VAT": "18%", "PAL_Gen": "Ex", "PAL_SG": "", "Cess_GEN": "40% or\nRs.180/=\nper kg", "Cess_SG": "", "Excise SPD": "", "SSCL": "2.5%", "SCL": "", "SC Code": ""}, {"Prefix": "", "HS Hdg Name": "Other vegetables, fresh or chilled.", "HS Hdg": "07.09", "HS Code": "0709.40.00N", "Description": "Celery other than celeriac", "Unit": "kg", "ICL/SLSI": "", "Preferential Duty_AP": "", "Preferential Duty_AD": "", "Preferential Duty_BN": "", "Preferential Duty_GT": "", "Preferential Duty_IN": "", "Preferential Duty_PK": "", "Preferential Duty_SA": "", "Preferential Duty_SF": "", "Preferential Duty_SD": "", "Preferential Duty_SG": "", "Gen Duty": "20%", "VAT": "18%", "PAL_Gen": "Ex", "PAL_SG": "", "Cess_GEN": "40% or\nRs.180/=\nper kg", "Cess_SG": "", "Excise SPD": "", "SSCL": "2.5%", "SCL": "", "SC Code": ""}, {"Prefix": "Mushrooms and truffles :", "HS Hdg Name": "Other vegetables, fresh or chilled.", "HS Hdg": "07.09", "HS Code": "0709.51.00N", "Description": "Mushrooms of the genus Agaricus", "Unit": "kg", "ICL/SLSI": "", "Preferential Duty_AP": "", "Preferential Duty_AD": "", "Preferential Duty_BN": "", "Preferential Duty_GT": "", "Preferential Duty_IN": "", "Preferential Duty_PK": "", "Preferential Duty_SA": "", "Preferential Duty_SF": "", "Preferential Duty_SD": "", "Preferential Duty_SG": "", "Gen Duty": "20%", "VAT": "18%", "PAL_Gen": "Ex", "PAL_SG": "", "Cess_GEN": "40% or\nRs.180/=\nper kg", "Cess_SG": "", "Excise SPD": "", "SSCL": "2.5%", "SCL": "", "SC Code": ""}, {"Prefix": "Mushrooms and truffles :", "HS Hdg Name": "Other vegetables, fresh or chilled.", "HS Hdg": "07.09", "HS Code": "0709.52.00N", "Description": "Mushrooms of the genus Boletus", "Unit": "kg", "ICL/SLSI": "", "Preferential Duty_AP": "", "Preferential Duty_AD": "", "Preferential Duty_BN": "", "Preferential Duty_GT": "", "Preferential Duty_IN": "", "Preferential Duty_PK": "Free", "Preferential Duty_SA": "", "Preferential Duty_SF": "5%", "Preferential Duty_SD": "5%", "Preferential Duty_SG": "", "Gen Duty": "20%", "VAT": "18%", "PAL_Gen": "Ex", "PAL_SG": "", "Cess_GEN": "40% or\nRs.180/=\nper kg", "Cess_SG": "", "Excise SPD": "", "SSCL": "2.5%", "SCL": "", "SC Code": ""}, {"Prefix": "Mushrooms and truffles :", "HS Hdg Name": "Other vegetables, fresh or chilled.", "HS Hdg": "07.09", "HS Code": "0709.53.00N", "Description": "Mushrooms of the genus Cantharellus", "Unit": "kg", "ICL/SLSI": "", "Preferential Duty_AP": "", "Preferential Duty_AD": "", "Preferential Duty_BN": "", "Preferential Duty_GT": "", "Preferential Duty_IN": "", "Preferential Duty_PK": "Free", "Preferential Duty_SA": "", "Preferential Duty_SF": "5%", "Preferential Duty_SD": "5%", "Preferential Duty_SG": "", "Gen Duty": "20%", "VAT": "18%", "PAL_Gen": "Ex", "PAL_SG": "", "Cess_GEN": "40% or\nRs.180/=\nper kg", "Cess_SG": "", "Excise SPD": "", "SSCL": "2.5%", "SCL": "", "SC Code": ""}, {"Prefix": "Mushrooms and truffles :", "HS Hdg Name": "Other vegetables, fresh or chilled.", "HS Hdg": "07.09", "HS Code": "0709.54.00N", "Description": "Shiitake (Lentinus edodes)", "Unit": "kg", "ICL/SLSI": "", "Preferential Duty_AP": "", "Preferential Duty_AD": "", "Preferential Duty_BN": "", "Preferential Duty_GT": "", "Preferential Duty_IN": "", "Preferential Duty_PK": "Free", "Preferential Duty_SA": "", "Preferential Duty_SF": "5%", "Preferential Duty_SD": "5%", "Preferential Duty_SG": "", "Gen Duty": "20%", "VAT": "18%", "PAL_Gen": "Ex", "PAL_SG": "", "Cess_GEN": "40% or\nRs.180/=\nper kg", "Cess_SG": "", "Excise SPD": "", "SSCL": "2.5%", "SCL": "", "SC Code": ""}, {"Prefix": "Mushrooms and truffles :", "HS Hdg Name": "Other vegetables, fresh or chilled.", "HS Hdg": "07.09", "HS Code": "0709.55.00N", "Description": "Matsutake (Tricholoma matsutake, Tricholoma\nmagnivelare, Tricholoma anatolicum, Tricholoma\ndulciolens, Tricholoma caligatum)", "Unit": "kg", "ICL/SLSI": "", "Preferential Duty_AP": "", "Preferential Duty_AD": "", "Preferential Duty_BN": "", "Preferential Duty_GT": "", "Preferential Duty_IN": "", "Preferential Duty_PK": "Free", "Preferential Duty_SA": "", "Preferential Duty_SF": "5%", "Preferential Duty_SD": "5%", "Preferential Duty_SG": "", "Gen Duty": "20%", "VAT": "18%", "PAL_Gen": "Ex", "PAL_SG": "", "Cess_GEN": "40% or\nRs.180/=\nper kg", "Cess_SG": "", "Excise SPD": "", "SSCL": "2.5%", "SCL": "", "SC Code": ""}, {"Prefix": "Mushrooms and truffles :", "HS Hdg Name": "Other vegetables, fresh or chilled.", "HS Hdg": "07.09", "HS Code": "0709.56.00N", "Description": "Truffles (Tuber spp.)", "Unit": "kg", "ICL/SLSI": "", "Preferential Duty_AP": "", "Preferential Duty_AD": "", "Preferential Duty_BN": "", "Preferential Duty_GT": "", "Preferential Duty_IN": "", "Preferential Duty_PK": "Free", "Preferential Duty_SA": "", "Preferential Duty_SF": "5%", "Preferential Duty_SD": "5%", "Preferential Duty_SG": "", "Gen Duty": "20%", "VAT": "18%", "PAL_Gen": "Ex", "PAL_SG": "", "Cess_GEN": "40% or\nRs.180/=\nper kg", "Cess_SG": "", "Excise SPD": "", "SSCL": "2.5%", "SCL": "", "SC Code": ""}, {"Prefix": "Mushrooms and truffles :", "HS Hdg Name": "Other vegetables, fresh or chilled.", "HS Hdg": "07.09", "HS Code": "0709.59.00N", "Description": "Other :", "Unit": "kg", "ICL/SLSI": "", "Preferential Duty_AP": "", "Preferential Duty_AD": "", "Preferential Duty_BN": "", "Preferential Duty_GT": "", "Preferential Duty_IN": "", "Preferential Duty_PK": "Free", "Preferential Duty_SA": "", "Preferential Duty_SF": "5%", "Preferential Duty_SD": "5%", "Preferential Duty_SG": "", "Gen Duty": "20%", "VAT": "18%", "PAL_Gen": "Ex", "PAL_SG": "", "Cess_GEN": "40% or\nRs.180/=\nper kg", "Cess_SG": "", "Excise SPD": "", "SSCL": "2.5%", "SCL": "", "SC Code": ""}, {"Prefix": "", "HS Hdg Name": "Other vegetables, fresh or chilled.", "HS Hdg": "07.09", "HS Code": "0709.60.00N", "Description": "Fruits of the genus Capsicum or of the genus\nPimenta", "Unit": "kg", "ICL/SLSI": "", "Preferential Duty_AP": "", "Preferential Duty_AD": "", "Preferential Duty_BN": "", "Preferential Duty_GT": "", "Preferential Duty_IN": "", "Preferential Duty_PK": "", "Preferential Duty_SA": "", "Preferential Duty_SF": "", "Preferential Duty_SD": "", "Preferential Duty_SG": "", "Gen Duty": "20%", "VAT": "18%", "PAL_Gen": "Ex", "PAL_SG": "", "Cess_GEN": "40% or\nRs.180/=\nper kg", "Cess_SG": "", "Excise SPD": "", "SSCL": "2.5%", "SCL": "", "SC Code": ""}, {"Prefix": "", "HS Hdg Name": "Other vegetables, fresh or chilled.", "HS Hdg": "07.09", "HS Code": "0709.70.00N", "Description": "Spinach, New Zealand spinach and orache spinach\n(garden spinach)", "Unit": "kg", "ICL/SLSI": "", "Preferential Duty_AP": "", "Preferential Duty_AD": "", "Preferential Duty_BN": "", "Preferential Duty_GT": "", "Preferential Duty_IN": "", "Preferential Duty_PK": "", "Preferential Duty_SA": "", "Preferential Duty_SF": "", "Preferential Duty_SD": "", "Preferential Duty_SG": "", "Gen Duty": "20%", "VAT": "18%", "PAL_Gen": "Ex", "PAL_SG": "", "Cess_GEN": "40% or\nRs.180/=\nper kg", "Cess_SG": "", "Excise SPD": "", "SSCL": "2.5%", "SCL": "", "SC Code": ""}, {"Prefix": "Other :", "HS Hdg Name": "Other vegetables, fresh or chilled.", "HS Hdg": "07.09", "HS Code": "0709.91.00N", "Description": "Globe artichokes", "Unit": "kg", "ICL/SLSI": "", "Preferential Duty_AP": "", "Preferential Duty_AD": "", "Preferential Duty_BN": "", "Preferential Duty_GT": "", "Preferential Duty_IN": "", "Preferential Duty_PK": "Free", "Preferential Duty_SA": "", "Preferential Duty_SF": "", "Preferential Duty_SD": "", "Preferential Duty_SG": "", "Gen Duty": "20%", "VAT": "18%", "PAL_Gen": "Ex", "PAL_SG": "", "Cess_GEN": "40% or\nRs.180/=\nper kg", "Cess_SG": "", "Excise SPD": "", "SSCL": "2.5%", "SCL": "", "SC Code": ""}, {"Prefix": "Other :", "HS Hdg Name": "Other vegetables, fresh or chilled.", "HS Hdg": "07.09", "HS Code": "0709.92.00N", "Description": "Olives", "Unit": "kg", "ICL/SLSI": "", "Preferential Duty_AP": "", "Preferential Duty_AD": "", "Preferential Duty_BN": "", "Preferential Duty_GT": "", "Preferential Duty_IN": "", "Preferential Duty_PK": "", "Preferential Duty_SA": "", "Preferential Duty_SF": "", "Preferential Duty_SD": "", "Preferential Duty_SG": "", "Gen Duty": "20%", "VAT": "18%", "PAL_Gen": "10%", "PAL_SG": "6%", "Cess_GEN": "40% or\nRs.180/=\nper kg", "Cess_SG": "24% or\nRs.88/= per\nkg", "Excise SPD": "", "SSCL": "2.5%", "SCL": "", "SC Code": ""}, {"Prefix": "Other :", "HS Hdg Name": "Other vegetables, fresh or chilled.", "HS Hdg": "07.09", "HS Code": "0709.93.00N", "Description": "Pumpkins, squash and gourds (Cucurbita spp.)", "Unit": "kg", "ICL/SLSI": "", "Preferential Duty_AP": "", "Preferential Duty_AD": "", "Preferential Duty_BN": "", "Preferential Duty_GT": "", "Preferential Duty_IN": "", "Preferential Duty_PK": "", "Preferential Duty_SA": "", "Preferential Duty_SF": "", "Preferential Duty_SD": "", "Preferential Duty_SG": "", "Gen Duty": "20%", "VAT": "18%", "PAL_Gen": "Ex", "PAL_SG": "", "Cess_GEN": "40% or\nRs.180/=\nper kg", "Cess_SG": "", "Excise SPD": "", "SSCL": "2.5%", "SCL": "", "SC Code": ""}, {"Prefix": "Sweet corn certified for sowing and rendered\ninedible by chemical treatment", "HS Hdg Name": "Other vegetables, fresh or chilled.", "HS Hdg": "07.09", "HS Code": "0709.99.12N", "Description": "Other", "Unit": "kg", "ICL/SLSI": "", "Preferential Duty_AP": "", "Preferential Duty_AD": "", "Preferential Duty_BN": "", "Preferential Duty_GT": "", "Preferential Duty_IN": "", "Preferential Duty_PK": "", "Preferential Duty_SA": "", "Preferential Duty_SF": "", "Preferential Duty_SD": "", "Preferential Duty_SG": "", "Gen Duty": "20%", "VAT": "18%", "PAL_Gen": "Ex", "PAL_SG": "", "Cess_GEN": "40% or\nRs.180/=\nper kg", "Cess_SG": "", "Excise SPD": "", "SSCL": "2.5%", "SCL": "", "SC Code": ""}, {"Prefix": "", "HS Hdg Name": "Other vegetables, fresh or chilled.", "HS Hdg": "07.09", "HS Code": "0709.99.20N", "Description": "Other", "Unit": "kg", "ICL/SLSI": "", "Preferential Duty_AP": "", "Preferential Duty_AD": "", "Preferential Duty_BN": "", "Preferential Duty_GT": "", "Preferential Duty_IN": "", "Preferential Duty_PK": "", "Preferential Duty_SA": "", "Preferential Duty_SF": "", "Preferential Duty_SD": "", "Preferential Duty_SG": "", "Gen Duty": "20%", "VAT": "18%", "PAL_Gen": "Ex", "PAL_SG": "", "Cess_GEN": "40% or\nRs.180/=\nper kg", "Cess_SG": "", "Excise SPD": "", "SSCL": "2.5%", "SCL": "", "SC Code": ""}, {"Prefix": "Potatoes :", "HS Hdg Name": "Vegetables (uncooked or cooked by steaming\nor boiling in water), frozen.", "HS Hdg": "07.10", "HS Code": "0710.10.10N", "Description": "Uncooked", "Unit": "kg", "ICL/SLSI": "", "Preferential Duty_AP": "", "Preferential Duty_AD": "", "Preferential Duty_BN": "", "Preferential Duty_GT": "", "Preferential Duty_IN": "", "Preferential Duty_PK": "", "Preferential Duty_SA": "", "Preferential Duty_SF": "", "Preferential Duty_SD": "", "Preferential Duty_SG": "", "Gen Duty": "Rs.60/=\nper kg", "VAT": "18%", "PAL_Gen": "Ex", "PAL_SG": "", "Cess_GEN": "25% or\nRs.180/=\nper kg", "Cess_SG": "", "Excise SPD": "", "SSCL": "2.5%", "SCL": "", "SC Code": ""}, {"Prefix": "Potatoes :", "HS Hdg Name": "Vegetables (uncooked or cooked by steaming\nor boiling in water), frozen.", "HS Hdg": "07.10", "HS Code": "0710.10.20N", "Description": "Cooked", "Unit": "kg", "ICL/SLSI": "", "Preferential Duty_AP": "", "Preferential Duty_AD": "", "Preferential Duty_BN": "", "Preferential Duty_GT": "", "Preferential Duty_IN": "", "Preferential Duty_PK": "", "Preferential Duty_SA": "", "Preferential Duty_SF": "", "Preferential Duty_SD": "", "Preferential Duty_SG": "", "Gen Duty": "Rs.60/=\nper kg", "VAT": "18%", "PAL_Gen": "Ex", "PAL_SG": "", "Cess_GEN": "25% or\nRs.180/=\nper kg", "Cess_SG": "", "Excise SPD": "", "SSCL": "2.5%", "SCL": "", "SC Code": ""}, {"Prefix": "Peas (Pisum sativum) :", "HS Hdg Name": "Vegetables (uncooked or cooked by steaming\nor boiling in water), frozen.", "HS Hdg": "07.10", "HS Code": "0710.21.10N", "Description": "Uncooked", "Unit": "kg", "ICL/SLSI": "", "Preferential Duty_AP": "", "Preferential Duty_AD": "", "Preferential Duty_BN": "", "Preferential Duty_GT": "", "Preferential Duty_IN": "", "Preferential Duty_PK": "Free", "Preferential Duty_SA": "", "Preferential Duty_SF": "", "Preferential Duty_SD": "", "Preferential Duty_SG": "", "Gen Duty": "20%", "VAT": "18%", "PAL_Gen": "10%", "PAL_SG": "", "Cess_GEN": "40% or\nRs.270/=\nper kg", "Cess_SG": "", "Excise SPD": "", "SSCL": "2.5%", "SCL": "", "SC Code": ""}, {"Prefix": "Peas (Pisum sativum) :", "HS Hdg Name": "Vegetables (uncooked or cooked by steaming\nor boiling in water), frozen.", "HS Hdg": "07.10", "HS Code": "0710.21.20N", "Description": "Cooked", "Unit": "kg", "ICL/SLSI": "", "Preferential Duty_AP": "", "Preferential Duty_AD": "", "Preferential Duty_BN": "", "Preferential Duty_GT": "", "Preferential Duty_IN": "", "Preferential Duty_PK": "Free", "Preferential Duty_SA": "", "Preferential Duty_SF": "", "Preferential Duty_SD": "", "Preferential Duty_SG": "", "Gen Duty": "20%", "VAT": "18%", "PAL_Gen": "Ex", "PAL_SG": "", "Cess_GEN": "40% or\nRs.270/=\nper kg", "Cess_SG": "", "Excise SPD": "", "SSCL": "2.5%", "SCL": "", "SC Code": ""}, {"Prefix": "Beans (Vigna spp., Phaseolus spp.) :", "HS Hdg Name": "Vegetables (uncooked or cooked by steaming\nor boiling in water), frozen.", "HS Hdg": "07.10", "HS Code": "0710.22.10N", "Description": "Uncooked", "Unit": "kg", "ICL/SLSI": "", "Preferential Duty_AP": "", "Preferential Duty_AD": "", "Preferential Duty_BN": "", "Preferential Duty_GT": "", "Preferential Duty_IN": "", "Preferential Duty_PK": "", "Preferential Duty_SA": "", "Preferential Duty_SF": "", "Preferential Duty_SD": "", "Preferential Duty_SG": "", "Gen Duty": "20%", "VAT": "18%", "PAL_Gen": "Ex", "PAL_SG": "", "Cess_GEN": "40% or\nRs.270/=\nper kg", "Cess_SG": "", "Excise SPD": "", "SSCL": "2.5%", "SCL": "", "SC Code": ""}, {"Prefix": "Beans (Vigna spp., Phaseolus spp.) :", "HS Hdg Name": "Vegetables (uncooked or cooked by steaming\nor boiling in water), frozen.", "HS Hdg": "07.10", "HS Code": "0710.22.20N", "Description": "Cooked", "Unit": "kg", "ICL/SLSI": "", "Preferential Duty_AP": "", "Preferential Duty_AD": "", "Preferential Duty_BN": "", "Preferential Duty_GT": "", "Preferential Duty_IN": "", "Preferential Duty_PK": "", "Preferential Duty_SA": "", "Preferential Duty_SF": "", "Preferential Duty_SD": "", "Preferential Duty_SG": "", "Gen Duty": "20%", "VAT": "18%", "PAL_Gen": "Ex", "PAL_SG": "", "Cess_GEN": "40% or\nRs.270/=\nper kg", "Cess_SG": "", "Excise SPD": "", "SSCL": "2.5%", "SCL": "", "SC Code": ""}, {"Prefix": "Other :", "HS Hdg Name": "Vegetables (uncooked or cooked by steaming\nor boiling in water), frozen.", "HS Hdg": "07.10", "HS Code": "0710.29.10N", "Description": "Uncooked", "Unit": "kg", "ICL/SLSI": "", "Preferential Duty_AP": "", "Preferential Duty_AD": "", "Preferential Duty_BN": "", "Preferential Duty_GT": "", "Preferential Duty_IN": "", "Preferential Duty_PK": "", "Preferential Duty_SA": "", "Preferential Duty_SF": "", "Preferential Duty_SD": "", "Preferential Duty_SG": "", "Gen Duty": "20%", "VAT": "18%", "PAL_Gen": "Ex", "PAL_SG": "", "Cess_GEN": "40% or\nRs.270/=\nper kg", "Cess_SG": "", "Excise SPD": "", "SSCL": "2.5%", "SCL": "", "SC Code": ""}, {"Prefix": "Other :", "HS Hdg Name": "Vegetables (uncooked or cooked by steaming\nor boiling in water), frozen.", "HS Hdg": "07.10", "HS Code": "0710.29.20N", "Description": "Cooked", "Unit": "kg", "ICL/SLSI": "", "Preferential Duty_AP": "", "Preferential Duty_AD": "", "Preferential Duty_BN": "", "Preferential Duty_GT": "", "Preferential Duty_IN": "", "Preferential Duty_PK": "", "Preferential Duty_SA": "", "Preferential Duty_SF": "", "Preferential Duty_SD": "", "Preferential Duty_SG": "", "Gen Duty": "20%", "VAT": "18%", "PAL_Gen": "Ex", "PAL_SG": "", "Cess_GEN": "40% or\nRs.270/=\nper kg", "Cess_SG": "", "Excise SPD": "", "SSCL": "2.5%", "SCL": "", "SC Code": ""}, {"Prefix": "Spinach, New Zealand spinach and orache spinach\n(garden spinach) :", "HS Hdg Name": "Vegetables (uncooked or cooked by steaming\nor boiling in water), frozen.", "HS Hdg": "07.10", "HS Code": "0710.30.10N", "Description": "Uncooked", "Unit": "kg", "ICL/SLSI": "", "Preferential Duty_AP": "", "Preferential Duty_AD": "", "Preferential Duty_BN": "", "Preferential Duty_GT": "", "Preferential Duty_IN": "", "Preferential Duty_PK": "", "Preferential Duty_SA": "", "Preferential Duty_SF": "", "Preferential Duty_SD": "", "Preferential Duty_SG": "", "Gen Duty": "20%", "VAT": "18%", "PAL_Gen": "Ex", "PAL_SG": "", "Cess_GEN": "40% or\nRs.270/=\nper kg", "Cess_SG": "", "Excise SPD": "", "SSCL": "2.5%", "SCL": "", "SC Code": ""}, {"Prefix": "Spinach, New Zealand spinach and orache spinach\n(garden spinach) :", "HS Hdg Name": "Vegetables (uncooked or cooked by steaming\nor boiling in water), frozen.", "HS Hdg": "07.10", "HS Code": "0710.30.20N", "Description": "Cooked", "Unit": "kg", "ICL/SLSI": "", "Preferential Duty_AP": "", "Preferential Duty_AD": "", "Preferential Duty_BN": "", "Preferential Duty_GT": "", "Preferential Duty_IN": "", "Preferential Duty_PK": "", "Preferential Duty_SA": "", "Preferential Duty_SF": "", "Preferential Duty_SD": "", "Preferential Duty_SG": "", "Gen Duty": "20%", "VAT": "18%", "PAL_Gen": "Ex", "PAL_SG": "", "Cess_GEN": "40% or\nRs.270/=\nper kg", "Cess_SG": "", "Excise SPD": "", "SSCL": "2.5%", "SCL": "", "SC Code": ""}, {"Prefix": "Sweet corn :", "HS Hdg Name": "Vegetables (uncooked or cooked by steaming\nor boiling in water), frozen.", "HS Hdg": "07.10", "HS Code": "0710.40.10N", "Description": "Uncooked", "Unit": "kg", "ICL/SLSI": "", "Preferential Duty_AP": "", "Preferential Duty_AD": "", "Preferential Duty_BN": "", "Preferential Duty_GT": "", "Preferential Duty_IN": "", "Preferential Duty_PK": "Free", "Preferential Duty_SA": "", "Preferential Duty_SF": "", "Preferential Duty_SD": "", "Preferential Duty_SG": "", "Gen Duty": "20%", "VAT": "18%", "PAL_Gen": "10%", "PAL_SG": "", "Cess_GEN": "40% or\nRs.270/=\nper kg", "Cess_SG": "", "Excise SPD": "", "SSCL": "2.5%", "SCL": "", "SC Code": ""}, {"Prefix": "Sweet corn :", "HS Hdg Name": "Vegetables (uncooked or cooked by steaming\nor boiling in water), frozen.", "HS Hdg": "07.10", "HS Code": "0710.40.20N", "Description": "Cooked", "Unit": "kg", "ICL/SLSI": "", "Preferential Duty_AP": "", "Preferential Duty_AD": "", "Preferential Duty_BN": "", "Preferential Duty_GT": "", "Preferential Duty_IN": "", "Preferential Duty_PK": "Free", "Preferential Duty_SA": "", "Preferential Duty_SF": "", "Preferential Duty_SD": "", "Preferential Duty_SG": "", "Gen Duty": "20%", "VAT": "18%", "PAL_Gen": "10%", "PAL_SG": "", "Cess_GEN": "40% or\nRs.270/=\nper kg", "Cess_SG": "", "Excise SPD": "", "SSCL": "2.5%", "SCL": "", "SC Code": ""}, {"Prefix": "Other Vegetables :", "HS Hdg Name": "Vegetables (uncooked or cooked by steaming\nor boiling in water), frozen.", "HS Hdg": "07.10", "HS Code": "0710.80.10N", "Description": "Uncooked", "Unit": "kg", "ICL/SLSI": "", "Preferential Duty_AP": "", "Preferential Duty_AD": "", "Preferential Duty_BN": "", "Preferential Duty_GT": "", "Preferential Duty_IN": "", "Preferential Duty_PK": "", "Preferential Duty_SA": "", "Preferential Duty_SF": "", "Preferential Duty_SD": "", "Preferential Duty_SG": "", "Gen Duty": "20%", "VAT": "18%", "PAL_Gen": "Ex", "PAL_SG": "", "Cess_GEN": "40% or\nRs.270/=\nper kg", "Cess_SG": "", "Excise SPD": "", "SSCL": "2.5%", "SCL": "", "SC Code": ""}, {"Prefix": "Other Vegetables :", "HS Hdg Name": "Vegetables (uncooked or cooked by steaming\nor boiling in water), frozen.", "HS Hdg": "07.10", "HS Code": "0710.80.20N", "Description": "Cooked", "Unit": "kg", "ICL/SLSI": "", "Preferential Duty_AP": "", "Preferential Duty_AD": "", "Preferential Duty_BN": "", "Preferential Duty_GT": "", "Preferential Duty_IN": "", "Preferential Duty_PK": "", "Preferential Duty_SA": "", "Preferential Duty_SF": "", "Preferential Duty_SD": "", "Preferential Duty_SG": "", "Gen Duty": "20%", "VAT": "18%", "PAL_Gen": "Ex", "PAL_SG": "", "Cess_GEN": "40% or\nRs.270/=\nper kg", "Cess_SG": "", "Excise SPD": "", "SSCL": "2.5%", "SCL": "", "SC Code": ""}, {"Prefix": "Mixtures of vegetables :", "HS Hdg Name": "Vegetables (uncooked or cooked by steaming\nor boiling in water), frozen.", "HS Hdg": "07.10", "HS Code": "0710.90.10N", "Description": "Uncooked", "Unit": "kg", "ICL/SLSI": "", "Preferential Duty_AP": "", "Preferential Duty_AD": "", "Preferential Duty_BN": "", "Preferential Duty_GT": "", "Preferential Duty_IN": "", "Preferential Duty_PK": "", "Preferential Duty_SA": "", "Preferential Duty_SF": "", "Preferential Duty_SD": "", "Preferential Duty_SG": "", "Gen Duty": "20%", "VAT": "18%", "PAL_Gen": "Ex", "PAL_SG": "", "Cess_GEN": "40% or\nRs.270/=\nper kg", "Cess_SG": "", "Excise SPD": "", "SSCL": "2.5%", "SCL": "", "SC Code": ""}, {"Prefix": "Mixtures of vegetables :", "HS Hdg Name": "Vegetables (uncooked or cooked by steaming\nor boiling in water), frozen.", "HS Hdg": "07.10", "HS Code": "0710.90.20N", "Description": "Cooked", "Unit": "kg", "ICL/SLSI": "", "Preferential Duty_AP": "", "Preferential Duty_AD": "", "Preferential Duty_BN": "", "Preferential Duty_GT": "", "Preferential Duty_IN": "", "Preferential Duty_PK": "", "Preferential Duty_SA": "", "Preferential Duty_SF": "", "Preferential Duty_SD": "", "Preferential Duty_SG": "", "Gen Duty": "20%", "VAT": "18%", "PAL_Gen": "Ex", "PAL_SG": "", "Cess_GEN": "40% or\nRs.270/=\nper kg", "Cess_SG": "", "Excise SPD": "", "SSCL": "2.5%", "SCL": "", "SC Code": ""}, {"Prefix": "", "HS Hdg Name": "Vegetables provisionally preserved, but\nunsuitable in that state for immediate\nconsumption.", "HS Hdg": "07.11", "HS Code": "0711.20.00N", "Description": "Olives", "Unit": "kg", "ICL/SLSI": "", "Preferential Duty_AP": "", "Preferential Duty_AD": "", "Preferential Duty_BN": "", "Preferential Duty_GT": "", "Preferential Duty_IN": "", "Preferential Duty_PK": "Free", "Preferential Duty_SA": "", "Preferential Duty_SF": "", "Preferential Duty_SD": "5%", "Preferential Duty_SG": "", "Gen Duty": "20%", "VAT": "18%", "PAL_Gen": "10%", "PAL_SG": "", "Cess_GEN": "40% or\nRs.270/=\nper kg", "Cess_SG": "", "Excise SPD": "", "SSCL": "2.5%", "SCL": "", "SC Code": ""}, {"Prefix": "Cucumbers and gherkins :", "HS Hdg Name": "Vegetables provisionally preserved, but\nunsuitable in that state for immediate\nconsumption.", "HS Hdg": "07.11", "HS Code": "0711.40.10N", "Description": "Cucumbers", "Unit": "kg", "ICL/SLSI": "", "Preferential Duty_AP": "", "Preferential Duty_AD": "", "Preferential Duty_BN": "", "Preferential Duty_GT": "", "Preferential Duty_IN": "", "Preferential Duty_PK": "", "Preferential Duty_SA": "", "Preferential Duty_SF": "", "Preferential Duty_SD": "", "Preferential Duty_SG": "", "Gen Duty": "20%", "VAT": "18%", "PAL_Gen": "Ex", "PAL_SG": "", "Cess_GEN": "40% or\nRs.270/=\nper kg", "Cess_SG": "", "Excise SPD": "", "SSCL": "2.5%", "SCL": "", "SC Code": ""}, {"Prefix": "Cucumbers and gherkins :", "HS Hdg Name": "Vegetables provisionally preserved, but\nunsuitable in that state for immediate\nconsumption.", "HS Hdg": "07.11", "HS Code": "0711.40.90N", "Description": "Gherkins", "Unit": "kg", "ICL/SLSI": "", "Preferential Duty_AP": "", "Preferential Duty_AD": "", "Preferential Duty_BN": "", "Preferential Duty_GT": "", "Preferential Duty_IN": "", "Preferential Duty_PK": "", "Preferential Duty_SA": "", "Preferential Duty_SF": "", "Preferential Duty_SD": "", "Preferential Duty_SG": "", "Gen Duty": "20%", "VAT": "18%", "PAL_Gen": "Ex", "PAL_SG": "", "Cess_GEN": "40% or\nRs.270/=\nper kg", "Cess_SG": "", "Excise SPD": "", "SSCL": "2.5%", "SCL": "", "SC Code": ""}, {"Prefix": "Mushrooms and truffles :", "HS Hdg Name": "Vegetables provisionally preserved, but\nunsuitable in that state for immediate\nconsumption.", "HS Hdg": "07.11", "HS Code": "0711.51.00N", "Description": "Mushrooms of the genus Agaricus", "Unit": "kg", "ICL/SLSI": "", "Preferential Duty_AP": "", "Preferential Duty_AD": "", "Preferential Duty_BN": "", "Preferential Duty_GT": "", "Preferential Duty_IN": "", "Preferential Duty_PK": "Free", "Preferential Duty_SA": "", "Preferential Duty_SF": "5%", "Preferential Duty_SD": "5%", "Preferential Duty_SG": "", "Gen Duty": "20%", "VAT": "18%", "PAL_Gen": "Ex", "PAL_SG": "", "Cess_GEN": "40% or\nRs.360/=\nper kg", "Cess_SG": "", "Excise SPD": "", "SSCL": "2.5%", "SCL": "", "SC Code": ""}, {"Prefix": "Mushrooms and truffles :", "HS Hdg Name": "Vegetables provisionally preserved, but\nunsuitable in that state for immediate\nconsumption.", "HS Hdg": "07.11", "HS Code": "0711.59.00N", "Description": "Other", "Unit": "kg", "ICL/SLSI": "", "Preferential Duty_AP": "", "Preferential Duty_AD": "", "Preferential Duty_BN": "", "Preferential Duty_GT": "", "Preferential Duty_IN": "", "Preferential Duty_PK": "Free", "Preferential Duty_SA": "", "Preferential Duty_SF": "5%", "Preferential Duty_SD": "5%", "Preferential Duty_SG": "", "Gen Duty": "20%", "VAT": "18%", "PAL_Gen": "Ex", "PAL_SG": "", "Cess_GEN": "40% or\nRs.360/=\nper kg", "Cess_SG": "", "Excise SPD": "", "SSCL": "2.5%", "SCL": "", "SC Code": ""}, {"Prefix": "Other vegetables; mixtures of vegetables :", "HS Hdg Name": "Vegetables provisionally preserved, but\nunsuitable in that state for immediate\nconsumption.", "HS Hdg": "07.11", "HS Code": "0711.90.10N", "Description": "Garlic", "Unit": "kg", "ICL/SLSI": "", "Preferential Duty_AP": "", "Preferential Duty_AD": "", "Preferential Duty_BN": "", "Preferential Duty_GT": "", "Preferential Duty_IN": "", "Preferential Duty_PK": "", "Preferential Duty_SA": "", "Preferential Duty_SF": "", "Preferential Duty_SD": "", "Preferential Duty_SG": "", "Gen Duty": "15% or\nRs.110\n/= per\nKg", "VAT": "18%", "PAL_Gen": "Ex", "PAL_SG": "", "Cess_GEN": "40% or\nRs.270/=\nper kg", "Cess_SG": "", "Excise SPD": "", "SSCL": "2.5%", "SCL": "", "SC Code": ""}, {"Prefix": "Other vegetables; mixtures of vegetables :", "HS Hdg Name": "Vegetables provisionally preserved, but\nunsuitable in that state for immediate\nconsumption.", "HS Hdg": "07.11", "HS Code": "0711.90.20N", "Description": "Onion", "Unit": "kg", "ICL/SLSI": "", "Preferential Duty_AP": "", "Preferential Duty_AD": "", "Preferential Duty_BN": "", "Preferential Duty_GT": "", "Preferential Duty_IN": "", "Preferential Duty_PK": "", "Preferential Duty_SA": "", "Preferential Duty_SF": "", "Preferential Duty_SD": "", "Preferential Duty_SG": "", "Gen Duty": "Rs.50/=\nper kg", "VAT": "18%", "PAL_Gen": "Ex", "PAL_SG": "", "Cess_GEN": "25% or\nRs.180/=\nper kg", "Cess_SG": "", "Excise SPD": "", "SSCL": "2.5%", "SCL": "", "SC Code": ""}, {"Prefix": "Other vegetables; mixtures of vegetables :", "HS Hdg Name": "Vegetables provisionally preserved, but\nunsuitable in that state for immediate\nconsumption.", "HS Hdg": "07.11", "HS Code": "0711.90.30N", "Description": "Capers", "Unit": "kg", "ICL/SLSI": "", "Preferential Duty_AP": "", "Preferential Duty_AD": "", "Preferential Duty_BN": "", "Preferential Duty_GT": "", "Preferential Duty_IN": "", "Preferential Duty_PK": "Free", "Preferential Duty_SA": "", "Preferential Duty_SF": "", "Preferential Duty_SD": "", "Preferential Duty_SG": "", "Gen Duty": "20%", "VAT": "18%", "PAL_Gen": "Ex", "PAL_SG": "", "Cess_GEN": "40% or\nRs.270/=\nper kg", "Cess_SG": "", "Excise SPD": "", "SSCL": "2.5%", "SCL": "", "SC Code": ""}, {"Prefix": "Other vegetables; mixtures of vegetables :", "HS Hdg Name": "Vegetables provisionally preserved, but\nunsuitable in that state for immediate\nconsumption.", "HS Hdg": "07.11", "HS Code": "0711.90.90N", "Description": "Other", "Unit": "kg", "ICL/SLSI": "", "Preferential Duty_AP": "", "Preferential Duty_AD": "", "Preferential Duty_BN": "", "Preferential Duty_GT": "", "Preferential Duty_IN": "", "Preferential Duty_PK": "", "Preferential Duty_SA": "", "Preferential Duty_SF": "", "Preferential Duty_SD": "", "Preferential Duty_SG": "", "Gen Duty": "20%", "VAT": "18%", "PAL_Gen": "10%", "PAL_SG": "", "Cess_GEN": "40% or\nRs.270/=\nper kg", "Cess_SG": "", "Excise SPD": "", "SSCL": "2.5%", "SCL": "", "SC Code": ""}, {"Prefix": "", "HS Hdg Name": "Dried vegetables, whole, cut, sliced, broken\nor in powder, but not further prepared.", "HS Hdg": "07.12", "HS Code": "0712.20.00N", "Description": "Onions", "Unit": "kg", "ICL/SLSI": "", "Preferential Duty_AP": "", "Preferential Duty_AD": "", "Preferential Duty_BN": "", "Preferential Duty_GT": "", "Preferential Duty_IN": "", "Preferential Duty_PK": "Free", "Preferential Duty_SA": "", "Preferential Duty_SF": "", "Preferential Duty_SD": "", "Preferential Duty_SG": "", "Gen Duty": "Rs.60/=\nper kg", "VAT": "18%", "PAL_Gen": "5%", "PAL_SG": "", "Cess_GEN": "Rs.150/=\nper kg", "Cess_SG": "", "Excise SPD": "", "SSCL": "2.5%", "SCL": "", "SC Code": ""}, {"Prefix": "Mushrooms, wood ears (Auricularia spp.), jelly\nfungi (Tremella spp.) and truffles :", "HS Hdg Name": "Dried vegetables, whole, cut, sliced, broken\nor in powder, but not further prepared.", "HS Hdg": "07.12", "HS Code": "0712.31.00N", "Description": "Mushrooms of the genus Agaricus", "Unit": "kg", "ICL/SLSI": "", "Preferential Duty_AP": "", "Preferential Duty_AD": "", "Preferential Duty_BN": "", "Preferential Duty_GT": "", "Preferential Duty_IN": "", "Preferential Duty_PK": "Free", "Preferential Duty_SA": "", "Preferential Duty_SF": "5%", "Preferential Duty_SD": "5%", "Preferential Duty_SG": "", "Gen Duty": "20%", "VAT": "18%", "PAL_Gen": "10%", "PAL_SG": "", "Cess_GEN": "40% or\nRs.360/=\nper kg", "Cess_SG": "", "Excise SPD": "", "SSCL": "2.5%", "SCL": "", "SC Code": ""}, {"Prefix": "Mushrooms, wood ears (Auricularia spp.), jelly\nfungi (Tremella spp.) and truffles :", "HS Hdg Name": "Dried vegetables, whole, cut, sliced, broken\nor in powder, but not further prepared.", "HS Hdg": "07.12", "HS Code": "0712.32.00N", "Description": "Wood ears (Auricularia spp.)", "Unit": "kg", "ICL/SLSI": "", "Preferential Duty_AP": "", "Preferential Duty_AD": "", "Preferential Duty_BN": "", "Preferential Duty_GT": "", "Preferential Duty_IN": "", "Preferential Duty_PK": "Free", "Preferential Duty_SA": "", "Preferential Duty_SF": "5%", "Preferential Duty_SD": "5%", "Preferential Duty_SG": "", "Gen Duty": "20%", "VAT": "18%", "PAL_Gen": "Ex", "PAL_SG": "", "Cess_GEN": "40% or\nRs.360/=\nper kg", "Cess_SG": "", "Excise SPD": "", "SSCL": "2.5%", "SCL": "", "SC Code": ""}, {"Prefix": "Mushrooms, wood ears (Auricularia spp.), jelly\nfungi (Tremella spp.) and truffles :", "HS Hdg Name": "Dried vegetables, whole, cut, sliced, broken\nor in powder, but not further prepared.", "HS Hdg": "07.12", "HS Code": "0712.33.00N", "Description": "Jelly fungi (Tremella spp.)", "Unit": "kg", "ICL/SLSI": "", "Preferential Duty_AP": "", "Preferential Duty_AD": "", "Preferential Duty_BN": "", "Preferential Duty_GT": "", "Preferential Duty_IN": "", "Preferential Duty_PK": "Free", "Preferential Duty_SA": "", "Preferential Duty_SF": "5%", "Preferential Duty_SD": "5%", "Preferential Duty_SG": "", "Gen Duty": "20%", "VAT": "18%", "PAL_Gen": "Ex", "PAL_SG": "", "Cess_GEN": "40% or\nRs.360/=\nper kg", "Cess_SG": "", "Excise SPD": "", "SSCL": "2.5%", "SCL": "", "SC Code": ""}, {"Prefix": "Mushrooms, wood ears (Auricularia spp.), jelly\nfungi (Tremella spp.) and truffles :", "HS Hdg Name": "Dried vegetables, whole, cut, sliced, broken\nor in powder, but not further prepared.", "HS Hdg": "07.12", "HS Code": "0712.34.00N", "Description": "Shiitake (Lentinus edodes)", "Unit": "kg", "ICL/SLSI": "", "Preferential Duty_AP": "", "Preferential Duty_AD": "", "Preferential Duty_BN": "", "Preferential Duty_GT": "", "Preferential Duty_IN": "", "Preferential Duty_PK": "Free", "Preferential Duty_SA": "", "Preferential Duty_SF": "5%", "Preferential Duty_SD": "5%", "Preferential Duty_SG": "", "Gen Duty": "20%", "VAT": "18%", "PAL_Gen": "Ex", "PAL_SG": "", "Cess_GEN": "40% or\nRs.360/=\nper kg", "Cess_SG": "", "Excise SPD": "", "SSCL": "2.5%", "SCL": "", "SC Code": ""}, {"Prefix": "Mushrooms, wood ears (Auricularia spp.), jelly\nfungi (Tremella spp.) and truffles :", "HS Hdg Name": "Dried vegetables, whole, cut, sliced, broken\nor in powder, but not further prepared.", "HS Hdg": "07.12", "HS Code": "0712.39.00N", "Description": "Other", "Unit": "kg", "ICL/SLSI": "", "Preferential Duty_AP": "", "Preferential Duty_AD": "", "Preferential Duty_BN": "", "Preferential Duty_GT": "", "Preferential Duty_IN": "", "Preferential Duty_PK": "Free", "Preferential Duty_SA": "", "Preferential Duty_SF": "5%", "Preferential Duty_SD": "5%", "Preferential Duty_SG": "", "Gen Duty": "20%", "VAT": "18%", "PAL_Gen": "Ex", "PAL_SG": "", "Cess_GEN": "40% or\nRs.360/=\nper kg", "Cess_SG": "", "Excise SPD": "", "SSCL": "2.5%", "SCL": "", "SC Code": ""}, {"Prefix": "Other vegetables; mixtures of vegetables :", "HS Hdg Name": "Dried vegetables, whole, cut, sliced, broken\nor in powder, but not further prepared.", "HS Hdg": "07.12", "HS Code": "0712.90.10N", "Description": "Garlic", "Unit": "kg", "ICL/SLSI": "", "Preferential Duty_AP": "", "Preferential Duty_AD": "", "Preferential Duty_BN": "", "Preferential Duty_GT": "", "Preferential Duty_IN": "", "Preferential Duty_PK": "", "Preferential Duty_SA": "", "Preferential Duty_SF": "", "Preferential Duty_SD": "", "Preferential Duty_SG": "", "Gen Duty": "15% or\nRs\n110/=\nper Kg", "VAT": "18%", "PAL_Gen": "5%", "PAL_SG": "", "Cess_GEN": "40% or\nRs.270/=\nper kg", "Cess_SG": "", "Excise SPD": "", "SSCL": "2.5%", "SCL": "", "SC Code": ""}, {"Prefix": "Other vegetables; mixtures of vegetables :", "HS Hdg Name": "Dried vegetables, whole, cut, sliced, broken\nor in powder, but not further prepared.", "HS Hdg": "07.12", "HS Code": "0712.90.90N", "Description": "Other", "Unit": "kg", "ICL/SLSI": "", "Preferential Duty_AP": "", "Preferential Duty_AD": "", "Preferential Duty_BN": "", "Preferential Duty_GT": "", "Preferential Duty_IN": "", "Preferential Duty_PK": "", "Preferential Duty_SA": "", "Preferential Duty_SF": "", "Preferential Duty_SD": "", "Preferential Duty_SG": "", "Gen Duty": "20%", "VAT": "18%", "PAL_Gen": "10%", "PAL_SG": "", "Cess_GEN": "Rs.450/=\nper kg", "Cess_SG": "", "Excise SPD": "", "SSCL": "2.5%", "SCL": "", "SC Code": ""}, {"Prefix": "Peas (Pisum sativum) :", "HS Hdg Name": "Dried leguminous vegetables, shelled,\nwhether or not skinned or split (+).", "HS Hdg": "07.13", "HS Code": "0713.10.10N", "Description": "Whole", "Unit": "kg", "ICL/SLSI": "", "Preferential Duty_AP": "", "Preferential Duty_AD": "", "Preferential Duty_BN": "", "Preferential Duty_GT": "", "Preferential Duty_IN": "", "Preferential Duty_PK": "", "Preferential Duty_SA": "", "Preferential Duty_SF": "", "Preferential Duty_SD": "", "Preferential Duty_SG": "", "Gen Duty": "20%", "VAT": "18%", "PAL_Gen": "Ex", "PAL_SG": "", "Cess_GEN": "10%", "Cess_SG": "", "Excise SPD": "", "SSCL": "2.5%", "SCL": "*", "SC Code": ""}, {"Prefix": "Peas (Pisum sativum) :", "HS Hdg Name": "Dried leguminous vegetables, shelled,\nwhether or not skinned or split (+).", "HS Hdg": "07.13", "HS Code": "0713.10.20N", "Description": "Split", "Unit": "kg", "ICL/SLSI": "", "Preferential Duty_AP": "", "Preferential Duty_AD": "", "Preferential Duty_BN": "", "Preferential Duty_GT": "", "Preferential Duty_IN": "", "Preferential Duty_PK": "", "Preferential Duty_SA": "", "Preferential Duty_SF": "", "Preferential Duty_SD": "", "Preferential Duty_SG": "", "Gen Duty": "20%", "VAT": "18%", "PAL_Gen": "Ex", "PAL_SG": "", "Cess_GEN": "10%", "Cess_SG": "", "Excise SPD": "", "SSCL": "2.5%", "SCL": "*", "SC Code": ""}, {"Prefix": "Chickpeas (garbanzos) :", "HS Hdg Name": "Dried leguminous vegetables, shelled,\nwhether or not skinned or split (+).", "HS Hdg": "07.13", "HS Code": "0713.20.10N", "Description": "Whole", "Unit": "kg", "ICL/SLSI": "", "Preferential Duty_AP": "", "Preferential Duty_AD": "", "Preferential Duty_BN": "", "Preferential Duty_GT": "", "Preferential Duty_IN": "", "Preferential Duty_PK": "Free", "Preferential Duty_SA": "", "Preferential Duty_SF": "", "Preferential Duty_SD": "", "Preferential Duty_SG": "", "Gen Duty": "15%", "VAT": "18%", "PAL_Gen": "Ex", "PAL_SG": "", "Cess_GEN": "0%", "Cess_SG": "", "Excise SPD": "", "SSCL": "2.5%", "SCL": "*", "SC Code": ""}, {"Prefix": "Chickpeas (garbanzos) :", "HS Hdg Name": "Dried leguminous vegetables, shelled,\nwhether or not skinned or split (+).", "HS Hdg": "07.13", "HS Code": "0713.20.20N", "Description": "Split", "Unit": "kg", "ICL/SLSI": "", "Preferential Duty_AP": "", "Preferential Duty_AD": "", "Preferential Duty_BN": "", "Preferential Duty_GT": "", "Preferential Duty_IN": "", "Preferential Duty_PK": "Free", "Preferential Duty_SA": "", "Preferential Duty_SF": "", "Preferential Duty_SD": "", "Preferential Duty_SG": "", "Gen Duty": "15%", "VAT": "18%", "PAL_Gen": "Ex", "PAL_SG": "", "Cess_GEN": "0%", "Cess_SG": "", "Excise SPD": "", "SSCL": "2.5%", "SCL": "*", "SC Code": ""}, {"Prefix": "Green gram (moong):", "HS Hdg Name": "Dried leguminous vegetables, shelled,\nwhether or not skinned or split (+).", "HS Hdg": "07.13", "HS Code": "0713.31.11N", "Description": "Beans certified for sowing and rendered inedible by\nchemical treatment", "Unit": "kg", "ICL/SLSI": "", "Preferential Duty_AP": "", "Preferential Duty_AD": "", "Preferential Duty_BN": "", "Preferential Duty_GT": "", "Preferential Duty_IN": "", "Preferential Duty_PK": "", "Preferential Duty_SA": "", "Preferential Duty_SF": "", "Preferential Duty_SD": "", "Preferential Duty_SG": "Free", "Gen Duty": "Free", "VAT": "18%", "PAL_Gen": "Ex", "PAL_SG": "", "Cess_GEN": "", "Cess_SG": "", "Excise SPD": "", "SSCL": "2.5%", "SCL": "", "SC Code": ""}, {"Prefix": "Green gram (moong):", "HS Hdg Name": "Dried leguminous vegetables, shelled,\nwhether or not skinned or split (+).", "HS Hdg": "07.13", "HS Code": "0713.31.19N", "Description": "Other", "Unit": "kg", "ICL/SLSI": "", "Preferential Duty_AP": "", "Preferential Duty_AD": "", "Preferential Duty_BN": "", "Preferential Duty_GT": "", "Preferential Duty_IN": "", "Preferential Duty_PK": "", "Preferential Duty_SA": "", "Preferential Duty_SF": "", "Preferential Duty_SD": "", "Preferential Duty_SG": "", "Gen Duty": "Rs.70/=\nper kg", "VAT": "18%", "PAL_Gen": "Ex", "PAL_SG": "", "Cess_GEN": "", "Cess_SG": "", "Excise SPD": "", "SSCL": "2.5%", "SCL": "*", "SC Code": ""}, {"Prefix": "Black gram :", "HS Hdg Name": "Dried leguminous vegetables, shelled,\nwhether or not skinned or split (+).", "HS Hdg": "07.13", "HS Code": "0713.31.21N", "Description": "Beans certified for sowing and rendered inedible by\nchemical treatment", "Unit": "kg", "ICL/SLSI": "", "Preferential Duty_AP": "", "Preferential Duty_AD": "", "Preferential Duty_BN": "", "Preferential Duty_GT": "", "Preferential Duty_IN": "", "Preferential Duty_PK": "", "Preferential Duty_SA": "", "Preferential Duty_SF": "", "Preferential Duty_SD": "", "Preferential Duty_SG": "Free", "Gen Duty": "Free", "VAT": "18%", "PAL_Gen": "Ex", "PAL_SG": "", "Cess_GEN": "", "Cess_SG": "", "Excise SPD": "", "SSCL": "2.5%", "SCL": "", "SC Code": ""}, {"Prefix": "Black gram :", "HS Hdg Name": "Dried leguminous vegetables, shelled,\nwhether or not skinned or split (+).", "HS Hdg": "07.13", "HS Code": "0713.31.22N", "Description": "Skinned, whether or not split", "Unit": "kg", "ICL/SLSI": "", "Preferential Duty_AP": "", "Preferential Duty_AD": "", "Preferential Duty_BN": "", "Preferential Duty_GT": "", "Preferential Duty_IN": "", "Preferential Duty_PK": "", "Preferential Duty_SA": "", "Preferential Duty_SF": "", "Preferential Duty_SD": "", "Preferential Duty_SG": "", "Gen Duty": "15%", "VAT": "18%", "PAL_Gen": "Ex", "PAL_SG": "", "Cess_GEN": "0%", "Cess_SG": "", "Excise SPD": "", "SSCL": "2.5%", "SCL": "*", "SC Code": ""}, {"Prefix": "Black gram :", "HS Hdg Name": "Dried leguminous vegetables, shelled,\nwhether or not skinned or split (+).", "HS Hdg": "07.13", "HS Code": "0713.31.29N", "Description": "Other", "Unit": "kg", "ICL/SLSI": "", "Preferential Duty_AP": "", "Preferential Duty_AD": "", "Preferential Duty_BN": "", "Preferential Duty_GT": "", "Preferential Duty_IN": "", "Preferential Duty_PK": "", "Preferential Duty_SA": "", "Preferential Duty_SF": "", "Preferential Duty_SD": "", "Preferential Duty_SG": "", "Gen Duty": "15%", "VAT": "18%", "PAL_Gen": "Ex", "PAL_SG": "", "Cess_GEN": "0%", "Cess_SG": "", "Excise SPD": "", "SSCL": "2.5%", "SCL": "*", "SC Code": ""}, {"Prefix": "", "HS Hdg Name": "Dried leguminous vegetables, shelled,\nwhether or not skinned or split (+).", "HS Hdg": "07.13", "HS Code": "0713.31.90N", "Description": "Other", "Unit": "kg", "ICL/SLSI": "", "Preferential Duty_AP": "", "Preferential Duty_AD": "", "Preferential Duty_BN": "", "Preferential Duty_GT": "", "Preferential Duty_IN": "", "Preferential Duty_PK": "", "Preferential Duty_SA": "", "Preferential Duty_SF": "", "Preferential Duty_SD": "", "Preferential Duty_SG": "", "Gen Duty": "20%", "VAT": "18%", "PAL_Gen": "Ex", "PAL_SG": "", "Cess_GEN": "10%", "Cess_SG": "", "Excise SPD": "", "SSCL": "2.5%", "SCL": "", "SC Code": ""}, {"Prefix": "Small red (Adzuki) beans (Phaseolus or Vigna\nangularis) :", "HS Hdg Name": "Dried leguminous vegetables, shelled,\nwhether or not skinned or split (+).", "HS Hdg": "07.13", "HS Code": "0713.32.10N", "Description": "Beans certified for sowing and rendered inedible by\nchemical treatment", "Unit": "kg", "ICL/SLSI": "", "Preferential Duty_AP": "", "Preferential Duty_AD": "", "Preferential Duty_BN": "", "Preferential Duty_GT": "", "Preferential Duty_IN": "", "Preferential Duty_PK": "", "Preferential Duty_SA": "", "Preferential Duty_SF": "Free", "Preferential Duty_SD": "", "Preferential Duty_SG": "Free", "Gen Duty": "Free", "VAT": "18%", "PAL_Gen": "Ex", "PAL_SG": "", "Cess_GEN": "", "Cess_SG": "", "Excise SPD": "", "SSCL": "2.5%", "SCL": "", "SC Code": ""}, {"Prefix": "Small red (Adzuki) beans (Phaseolus or Vigna\nangularis) :", "HS Hdg Name": "Dried leguminous vegetables, shelled,\nwhether or not skinned or split (+).", "HS Hdg": "07.13", "HS Code": "0713.32.90N", "Description": "Other", "Unit": "kg", "ICL/SLSI": "", "Preferential Duty_AP": "", "Preferential Duty_AD": "", "Preferential Duty_BN": "", "Preferential Duty_GT": "", "Preferential Duty_IN": "", "Preferential Duty_PK": "", "Preferential Duty_SA": "", "Preferential Duty_SF": "Free", "Preferential Duty_SD": "", "Preferential Duty_SG": "", "Gen Duty": "20%", "VAT": "18%", "PAL_Gen": "10%", "PAL_SG": "", "Cess_GEN": "10%", "Cess_SG": "", "Excise SPD": "", "SSCL": "2.5%", "SCL": "", "SC Code": ""}, {"Prefix": "Kidney beans, including white pea beans\n(Phaseolus vulgaris):", "HS Hdg Name": "Dried leguminous vegetables, shelled,\nwhether or not skinned or split (+).", "HS Hdg": "07.13", "HS Code": "0713.33.10N", "Description": "Beans certified for sowing and rendered inedible by\nchemical treatment", "Unit": "kg", "ICL/SLSI": "", "Preferential Duty_AP": "", "Preferential Duty_AD": "", "Preferential Duty_BN": "", "Preferential Duty_GT": "", "Preferential Duty_IN": "", "Preferential Duty_PK": "", "Preferential Duty_SA": "", "Preferential Duty_SF": "Free", "Preferential Duty_SD": "", "Preferential Duty_SG": "Free", "Gen Duty": "Free", "VAT": "Ex", "PAL_Gen": "Ex", "PAL_SG": "", "Cess_GEN": "", "Cess_SG": "", "Excise SPD": "", "SSCL": "2.5%", "SCL": "", "SC Code": "SC000"}, {"Prefix": "Kidney beans, including white pea beans\n(Phaseolus vulgaris):", "HS Hdg Name": "Dried leguminous vegetables, shelled,\nwhether or not skinned or split (+).", "HS Hdg": "07.13", "HS Code": "0713.33.90N", "Description": "Other", "Unit": "kg", "ICL/SLSI": "", "Preferential Duty_AP": "", "Preferential Duty_AD": "", "Preferential Duty_BN": "", "Preferential Duty_GT": "", "Preferential Duty_IN": "", "Preferential Duty_PK": "", "Preferential Duty_SA": "", "Preferential Duty_SF": "Free", "Preferential Duty_SD": "", "Preferential Duty_SG": "", "Gen Duty": "20%", "VAT": "18%", "PAL_Gen": "10%", "PAL_SG": "", "Cess_GEN": "10%", "Cess_SG": "", "Excise SPD": "", "SSCL": "2.5%", "SCL": "", "SC Code": ""}, {"Prefix": "Bambara beans (Vigna subterranea or Voandzeia\nsubterranea) :", "HS Hdg Name": "Dried leguminous vegetables, shelled,\nwhether or not skinned or split (+).", "HS Hdg": "07.13", "HS Code": "0713.34.10N", "Description": "Beans certified for sowing and rendered inedible by\nchemical treatment", "Unit": "kg", "ICL/SLSI": "", "Preferential Duty_AP": "", "Preferential Duty_AD": "", "Preferential Duty_BN": "", "Preferential Duty_GT": "", "Preferential Duty_IN": "", "Preferential Duty_PK": "", "Preferential Duty_SA": "", "Preferential Duty_SF": "", "Preferential Duty_SD": "", "Preferential Duty_SG": "Free", "Gen Duty": "Free", "VAT": "18%", "PAL_Gen": "Ex", "PAL_SG": "", "Cess_GEN": "", "Cess_SG": "", "Excise SPD": "", "SSCL": "2.5%", "SCL": "", "SC Code": ""}, {"Prefix": "Bambara beans (Vigna subterranea or Voandzeia\nsubterranea) :", "HS Hdg Name": "Dried leguminous vegetables, shelled,\nwhether or not skinned or split (+).", "HS Hdg": "07.13", "HS Code": "0713.34.90N", "Description": "Other", "Unit": "kg", "ICL/SLSI": "", "Preferential Duty_AP": "", "Preferential Duty_AD": "", "Preferential Duty_BN": "", "Preferential Duty_GT": "", "Preferential Duty_IN": "", "Preferential Duty_PK": "", "Preferential Duty_SA": "", "Preferential Duty_SF": "", "Preferential Duty_SD": "", "Preferential Duty_SG": "", "Gen Duty": "20%", "VAT": "18%", "PAL_Gen": "Ex", "PAL_SG": "", "Cess_GEN": "10%", "Cess_SG": "", "Excise SPD": "", "SSCL": "2.5%", "SCL": "", "SC Code": ""}, {"Prefix": "Cow peas (Vigna unguiculata) :", "HS Hdg Name": "Dried leguminous vegetables, shelled,\nwhether or not skinned or split (+).", "HS Hdg": "07.13", "HS Code": "0713.35.10N", "Description": "Beans certified for sowing and rendered inedible by\nchemical treatment", "Unit": "kg", "ICL/SLSI": "", "Preferential Duty_AP": "", "Preferential Duty_AD": "", "Preferential Duty_BN": "", "Preferential Duty_GT": "", "Preferential Duty_IN": "", "Preferential Duty_PK": "", "Preferential Duty_SA": "", "Preferential Duty_SF": "", "Preferential Duty_SD": "", "Preferential Duty_SG": "Free", "Gen Duty": "Free", "VAT": "18%", "PAL_Gen": "Ex", "PAL_SG": "", "Cess_GEN": "", "Cess_SG": "", "Excise SPD": "", "SSCL": "2.5%", "SCL": "", "SC Code": ""}, {"Prefix": "Cow peas (Vigna unguiculata) :", "HS Hdg Name": "Dried leguminous vegetables, shelled,\nwhether or not skinned or split (+).", "HS Hdg": "07.13", "HS Code": "0713.35.90N", "Description": "Other", "Unit": "kg", "ICL/SLSI": "", "Preferential Duty_AP": "", "Preferential Duty_AD": "", "Preferential Duty_BN": "", "Preferential Duty_GT": "", "Preferential Duty_IN": "", "Preferential Duty_PK": "", "Preferential Duty_SA": "", "Preferential Duty_SF": "", "Preferential Duty_SD": "", "Preferential Duty_SG": "", "Gen Duty": "Rs.70/=\nper kg", "VAT": "18%", "PAL_Gen": "Ex", "PAL_SG": "", "Cess_GEN": "", "Cess_SG": "", "Excise SPD": "", "SSCL": "2.5%", "SCL": "*", "SC Code": ""}, {"Prefix": "Other :", "HS Hdg Name": "Dried leguminous vegetables, shelled,\nwhether or not skinned or split (+).", "HS Hdg": "07.13", "HS Code": "0713.39.10N", "Description": "Beans certified for sowing and rendered inedible by\nchemical treatment", "Unit": "kg", "ICL/SLSI": "", "Preferential Duty_AP": "", "Preferential Duty_AD": "", "Preferential Duty_BN": "", "Preferential Duty_GT": "", "Preferential Duty_IN": "", "Preferential Duty_PK": "", "Preferential Duty_SA": "", "Preferential Duty_SF": "", "Preferential Duty_SD": "", "Preferential Duty_SG": "Free", "Gen Duty": "Free", "VAT": "18%", "PAL_Gen": "Ex", "PAL_SG": "", "Cess_GEN": "", "Cess_SG": "", "Excise SPD": "", "SSCL": "2.5%", "SCL": "", "SC Code": ""}, {"Prefix": "Other :", "HS Hdg Name": "Dried leguminous vegetables, shelled,\nwhether or not skinned or split (+).", "HS Hdg": "07.13", "HS Code": "0713.39.90N", "Description": "Other", "Unit": "Kg", "ICL/SLSI": "", "Preferential Duty_AP": "", "Preferential Duty_AD": "", "Preferential Duty_BN": "", "Preferential Duty_GT": "", "Preferential Duty_IN": "", "Preferential Duty_PK": "", "Preferential Duty_SA": "", "Preferential Duty_SF": "", "Preferential Duty_SD": "", "Preferential Duty_SG": "", "Gen Duty": "20%", "VAT": "18%", "PAL_Gen": "10%", "PAL_SG": "", "Cess_GEN": "10%", "Cess_SG": "", "Excise SPD": "", "SSCL": "2.5%", "SCL": "", "SC Code": ""}, {"Prefix": "Massor dhal (red lentils) whole or split :", "HS Hdg Name": "Dried leguminous vegetables, shelled,\nwhether or not skinned or split (+).", "HS Hdg": "07.13", "HS Code": "0713.40.11N", "Description": "Whole", "Unit": "kg", "ICL/SLSI": "", "Preferential Duty_AP": "", "Preferential Duty_AD": "", "Preferential Duty_BN": "", "Preferential Duty_GT": "", "Preferential Duty_IN": "", "Preferential Duty_PK": "", "Preferential Duty_SA": "", "Preferential Duty_SF": "", "Preferential Duty_SD": "Free", "Preferential Duty_SG": "", "Gen Duty": "Free", "VAT": "18%", "PAL_Gen": "Ex", "PAL_SG": "", "Cess_GEN": "", "Cess_SG": "", "Excise SPD": "", "SSCL": "2.5%", "SCL": "*", "SC Code": ""}, {"Prefix": "Massor dhal (red lentils) whole or split :", "HS Hdg Name": "Dried leguminous vegetables, shelled,\nwhether or not skinned or split (+).", "HS Hdg": "07.13", "HS Code": "0713.40.12N", "Description": "Split", "Unit": "kg", "ICL/SLSI": "", "Preferential Duty_AP": "", "Preferential Duty_AD": "", "Preferential Duty_BN": "", "Preferential Duty_GT": "", "Preferential Duty_IN": "", "Preferential Duty_PK": "", "Preferential Duty_SA": "", "Preferential Duty_SF": "", "Preferential Duty_SD": "Free", "Preferential Duty_SG": "", "Gen Duty": "Free", "VAT": "18%", "PAL_Gen": "Ex", "PAL_SG": "", "Cess_GEN": "", "Cess_SG": "", "Excise SPD": "", "SSCL": "2.5%", "SCL": "*", "SC Code": ""}, {"Prefix": "Whole or split yellow lentils :", "HS Hdg Name": "Dried leguminous vegetables, shelled,\nwhether or not skinned or split (+).", "HS Hdg": "07.13", "HS Code": "0713.40.21N", "Description": "Whole", "Unit": "kg", "ICL/SLSI": "", "Preferential Duty_AP": "", "Preferential Duty_AD": "", "Preferential Duty_BN": "", "Preferential Duty_GT": "", "Preferential Duty_IN": "", "Preferential Duty_PK": "", "Preferential Duty_SA": "", "Preferential Duty_SF": "", "Preferential Duty_SD": "Free", "Preferential Duty_SG": "", "Gen Duty": "Free", "VAT": "18%", "PAL_Gen": "Ex", "PAL_SG": "", "Cess_GEN": "", "Cess_SG": "", "Excise SPD": "", "SSCL": "2.5%", "SCL": "*", "SC Code": ""}, {"Prefix": "Whole or split yellow lentils :", "HS Hdg Name": "Dried leguminous vegetables, shelled,\nwhether or not skinned or split (+).", "HS Hdg": "07.13", "HS Code": "0713.40.22N", "Description": "Split", "Unit": "kg", "ICL/SLSI": "", "Preferential Duty_AP": "", "Preferential Duty_AD": "", "Preferential Duty_BN": "", "Preferential Duty_GT": "", "Preferential Duty_IN": "", "Preferential Duty_PK": "", "Preferential Duty_SA": "", "Preferential Duty_SF": "", "Preferential Duty_SD": "Free", "Preferential Duty_SG": "", "Gen Duty": "Free", "VAT": "18%", "PAL_Gen": "Ex", "PAL_SG": "", "Cess_GEN": "", "Cess_SG": "", "Excise SPD": "", "SSCL": "2.5%", "SCL": "*", "SC Code": ""}, {"Prefix": "Whole or split yellow lentils :", "HS Hdg Name": "Dried leguminous vegetables, shelled,\nwhether or not skinned or split (+).", "HS Hdg": "07.13", "HS Code": "0713.40.90N", "Description": "Other", "Unit": "kg", "ICL/SLSI": "", "Preferential Duty_AP": "", "Preferential Duty_AD": "", "Preferential Duty_BN": "", "Preferential Duty_GT": "", "Preferential Duty_IN": "", "Preferential Duty_PK": "", "Preferential Duty_SA": "", "Preferential Duty_SF": "", "Preferential Duty_SD": "22.4%", "Preferential Duty_SG": "", "Gen Duty": "20%", "VAT": "18%", "PAL_Gen": "Ex", "PAL_SG": "", "Cess_GEN": "10%", "Cess_SG": "", "Excise SPD": "", "SSCL": "2.5%", "SCL": "", "SC Code": ""}, {"Prefix": "", "HS Hdg Name": "Dried leguminous vegetables, shelled,\nwhether or not skinned or split (+).", "HS Hdg": "07.13", "HS Code": "0713.50.00N", "Description": "Broad beans (Vicia faba var. major) and horse\nbeans (Vicia faba var. equina, Vicia faba var.\nminor)", "Unit": "kg", "ICL/SLSI": "", "Preferential Duty_AP": "", "Preferential Duty_AD": "", "Preferential Duty_BN": "", "Preferential Duty_GT": "", "Preferential Duty_IN": "", "Preferential Duty_PK": "Free", "Preferential Duty_SA": "", "Preferential Duty_SF": "", "Preferential Duty_SD": "", "Preferential Duty_SG": "", "Gen Duty": "20%", "VAT": "18%", "PAL_Gen": "10%", "PAL_SG": "", "Cess_GEN": "10%", "Cess_SG": "", "Excise SPD": "", "SSCL": "2.5%", "SCL": "", "SC Code": ""}, {"Prefix": "Pigeon peas (Cajanus cajan) :", "HS Hdg Name": "Dried leguminous vegetables, shelled,\nwhether or not skinned or split (+).", "HS Hdg": "07.13", "HS Code": "0713.60.10N", "Description": "Toor Dhal", "Unit": "kg", "ICL/SLSI": "", "Preferential Duty_AP": "", "Preferential Duty_AD": "", "Preferential Duty_BN": "", "Preferential Duty_GT": "", "Preferential Duty_IN": "", "Preferential Duty_PK": "", "Preferential Duty_SA": "", "Preferential Duty_SF": "", "Preferential Duty_SD": "", "Preferential Duty_SG": "", "Gen Duty": "Rs.45/=\nper kg", "VAT": "18%", "PAL_Gen": "10%", "PAL_SG": "6%", "Cess_GEN": "", "Cess_SG": "", "Excise SPD": "", "SSCL": "2.5%", "SCL": "", "SC Code": ""}, {"Prefix": "Pigeon peas (Cajanus cajan) :", "HS Hdg Name": "Dried leguminous vegetables, shelled,\nwhether or not skinned or split (+).", "HS Hdg": "07.13", "HS Code": "0713.60.90N", "Description": "Other", "Unit": "kg", "ICL/SLSI": "", "Preferential Duty_AP": "", "Preferential Duty_AD": "", "Preferential Duty_BN": "", "Preferential Duty_GT": "", "Preferential Duty_IN": "", "Preferential Duty_PK": "", "Preferential Duty_SA": "", "Preferential Duty_SF": "", "Preferential Duty_SD": "", "Preferential Duty_SG": "", "Gen Duty": "20%", "VAT": "18%", "PAL_Gen": "10%", "PAL_SG": "", "Cess_GEN": "10%", "Cess_SG": "", "Excise SPD": "", "SSCL": "2.5%", "SCL": "", "SC Code": ""}, {"Prefix": "", "HS Hdg Name": "Dried leguminous vegetables, shelled,\nwhether or not skinned or split (+).", "HS Hdg": "07.13", "HS Code": "0713.90.00N", "Description": "Other", "Unit": "kg", "ICL/SLSI": "", "Preferential Duty_AP": "", "Preferential Duty_AD": "", "Preferential Duty_BN": "", "Preferential Duty_GT": "", "Preferential Duty_IN": "", "Preferential Duty_PK": "", "Preferential Duty_SA": "", "Preferential Duty_SF": "", "Preferential Duty_SD": "", "Preferential Duty_SG": "", "Gen Duty": "20%", "VAT": "18%", "PAL_Gen": "10%", "PAL_SG": "", "Cess_GEN": "10%", "Cess_SG": "", "Excise SPD": "", "SSCL": "2.5%", "SCL": "", "SC Code": ""}, {"Prefix": "", "HS Hdg Name": "Manioc, arrowroot, salep, Jerusalem\nartichokes, sweet potatoes and similar roots\nand tubers with high starch or inulin content,\nfresh, chilled, frozen or dried, whether or not\nsliced or in the form of pellets; sago pith.", "HS Hdg": "07.14", "HS Code": "0714.10.00N", "Description": "Manioc (cassava)", "Unit": "kg", "ICL/SLSI": "", "Preferential Duty_AP": "", "Preferential Duty_AD": "", "Preferential Duty_BN": "", "Preferential Duty_GT": "", "Preferential Duty_IN": "", "Preferential Duty_PK": "", "Preferential Duty_SA": "", "Preferential Duty_SF": "", "Preferential Duty_SD": "", "Preferential Duty_SG": "", "Gen Duty": "20%", "VAT": "18%", "PAL_Gen": "Ex", "PAL_SG": "", "Cess_GEN": "25% or\nRs.180/=\nper kg", "Cess_SG": "", "Excise SPD": "", "SSCL": "2.5%", "SCL": "", "SC Code": ""}, {"Prefix": "", "HS Hdg Name": "Manioc, arrowroot, salep, Jerusalem\nartichokes, sweet potatoes and similar roots\nand tubers with high starch or inulin content,\nfresh, chilled, frozen or dried, whether or not\nsliced or in the form of pellets; sago pith.", "HS Hdg": "07.14", "HS Code": "0714.20.00N", "Description": "Sweet potatoes", "Unit": "kg", "ICL/SLSI": "", "Preferential Duty_AP": "", "Preferential Duty_AD": "", "Preferential Duty_BN": "", "Preferential Duty_GT": "", "Preferential Duty_IN": "", "Preferential Duty_PK": "", "Preferential Duty_SA": "", "Preferential Duty_SF": "", "Preferential Duty_SD": "", "Preferential Duty_SG": "", "Gen Duty": "20%", "VAT": "18%", "PAL_Gen": "Ex", "PAL_SG": "", "Cess_GEN": "25% or\nRs.180/=\nper kg", "Cess_SG": "", "Excise SPD": "", "SSCL": "2.5%", "SCL": "", "SC Code": ""}, {"Prefix": "", "HS Hdg Name": "Manioc, arrowroot, salep, Jerusalem\nartichokes, sweet potatoes and similar roots\nand tubers with high starch or inulin content,\nfresh, chilled, frozen or dried, whether or not\nsliced or in the form of pellets; sago pith.", "HS Hdg": "07.14", "HS Code": "0714.30.00N", "Description": "Yams (Dioscorea spp.)", "Unit": "kg", "ICL/SLSI": "", "Preferential Duty_AP": "", "Preferential Duty_AD": "", "Preferential Duty_BN": "", "Preferential Duty_GT": "", "Preferential Duty_IN": "", "Preferential Duty_PK": "", "Preferential Duty_SA": "", "Preferential Duty_SF": "", "Preferential Duty_SD": "", "Preferential Duty_SG": "", "Gen Duty": "20%", "VAT": "18%", "PAL_Gen": "Ex", "PAL_SG": "", "Cess_GEN": "25% or\nRs.180/=\nper kg", "Cess_SG": "", "Excise SPD": "", "SSCL": "2.5%", "SCL": "", "SC Code": ""}, {"Prefix": "", "HS Hdg Name": "Manioc, arrowroot, salep, Jerusalem\nartichokes, sweet potatoes and similar roots\nand tubers with high starch or inulin content,\nfresh, chilled, frozen or dried, whether or not\nsliced or in the form of pellets; sago pith.", "HS Hdg": "07.14", "HS Code": "0714.40.00N", "Description": "Taro (Colocasia spp.)", "Unit": "kg", "ICL/SLSI": "", "Preferential Duty_AP": "", "Preferential Duty_AD": "", "Preferential Duty_BN": "", "Preferential Duty_GT": "", "Preferential Duty_IN": "", "Preferential Duty_PK": "", "Preferential Duty_SA": "", "Preferential Duty_SF": "", "Preferential Duty_SD": "", "Preferential Duty_SG": "", "Gen Duty": "20%", "VAT": "18%", "PAL_Gen": "Ex", "PAL_SG": "", "Cess_GEN": "25% or\nRs.180/=\nper kg", "Cess_SG": "", "Excise SPD": "", "SSCL": "2.5%", "SCL": "", "SC Code": ""}, {"Prefix": "", "HS Hdg Name": "Manioc, arrowroot, salep, Jerusalem\nartichokes, sweet potatoes and similar roots\nand tubers with high starch or inulin content,\nfresh, chilled, frozen or dried, whether or not\nsliced or in the form of pellets; sago pith.", "HS Hdg": "07.14", "HS Code": "0714.50.00N", "Description": "Yautia (Xanthosoma spp.)", "Unit": "kg", "ICL/SLSI": "", "Preferential Duty_AP": "", "Preferential Duty_AD": "", "Preferential Duty_BN": "", "Preferential Duty_GT": "", "Preferential Duty_IN": "", "Preferential Duty_PK": "", "Preferential Duty_SA": "", "Preferential Duty_SF": "", "Preferential Duty_SD": "", "Preferential Duty_SG": "", "Gen Duty": "20%", "VAT": "18%", "PAL_Gen": "Ex", "PAL_SG": "", "Cess_GEN": "25% or\nRs.180/=\nper kg", "Cess_SG": "", "Excise SPD": "", "SSCL": "2.5%", "SCL": "", "SC Code": ""}, {"Prefix": "", "HS Hdg Name": "Manioc, arrowroot, salep, Jerusalem\nartichokes, sweet potatoes and similar roots\nand tubers with high starch or inulin content,\nfresh, chilled, frozen or dried, whether or not\nsliced or in the form of pellets; sago pith.", "HS Hdg": "07.14", "HS Code": "0714.90.00N", "Description": "Other", "Unit": "kg", "ICL/SLSI": "", "Preferential Duty_AP": "", "Preferential Duty_AD": "", "Preferential Duty_BN": "", "Preferential Duty_GT": "", "Preferential Duty_IN": "", "Preferential Duty_PK": "Free", "Preferential Duty_SA": "", "Preferential Duty_SF": "", "Preferential Duty_SD": "", "Preferential Duty_SG": "", "Gen Duty": "20%", "VAT": "18%", "PAL_Gen": "Ex", "PAL_SG": "", "Cess_GEN": "25% or\nRs.180/=\nper kg", "Cess_SG": "", "Excise SPD": "", "SSCL": "2.5%", "SCL": "", "SC Code": ""}]}